{
  "id": "f1_monaco",
  "name": "Circuit de Monaco",
  "trackLength": 3263,
  "turns": 19,
  "paths": [
    {
      "id": "f1_monaco_path_0",
      "anchors": [
        {
          "id": "a_mp3x0l5z_0",
          "point": {
            "x": 126.32176907601699,
            "y": 203.12830399941035
          },
          "inHandle": {
            "x": 126.32176907601699,
            "y": 203.12830399941035
          },
          "outHandle": {
            "x": 126.32176907601699,
            "y": 203.12830399941035
          },
          "handleType": "corner"
        },
        {
          "id": "a_mp3x0l5z_1",
          "point": {
            "x": 112.76116567579555,
            "y": 182.12568427181677
          },
          "inHandle": {
            "x": 117.07785437540804,
            "y": 189.24423535048223
          },
          "outHandle": {
            "x": 108.44447697618307,
            "y": 175.0071331931513
          },
          "handleType": "smooth"
        },
        {
          "id": "a_mp3x0l5z_2",
          "point": {
            "x": 100.42163687834206,
            "y": 160.41699752741755
          },
          "inHandle": {
            "x": 103.85334581762136,
            "y": 167.95363410803333
          },
          "outHandle": {
            "x": 96.98992793906275,
            "y": 152.88036094680177
          },
          "handleType": "smooth"
        },
        {
          "id": "a_mp3x0l5z_3",
          "point": {
            "x": 92.17091204011972,
            "y": 136.90586478812213
          },
          "inHandle": {
            "x": 94.68969353766083,
            "y": 144.83102531960276
          },
          "outHandle": {
            "x": 89.6521305425786,
            "y": 128.9807042566415
          },
          "handleType": "smooth"
        },
        {
          "id": "a_mp3x0l5z_4",
          "point": {
            "x": 85.30894789309536,
            "y": 112.86603433853384
          },
          "inHandle": {
            "x": 87.59626927543681,
            "y": 120.87931115506326
          },
          "outHandle": {
            "x": 83.02162651075392,
            "y": 104.85275752200441
          },
          "handleType": "smooth"
        },
        {
          "id": "a_mp3x0l5z_5",
          "point": {
            "x": 78.44698374607101,
            "y": 88.82620388894554
          },
          "inHandle": {
            "x": 80.73430512841246,
            "y": 96.83948070547497
          },
          "outHandle": {
            "x": 76.15966236372957,
            "y": 80.81292707241612
          },
          "handleType": "smooth"
        },
        {
          "id": "a_mp3x0l5z_6",
          "point": {
            "x": 71.58501959904666,
            "y": 64.78637343935725
          },
          "inHandle": {
            "x": 73.74521715224729,
            "y": 72.8288955905131
          },
          "outHandle": {
            "x": 69.42482204584603,
            "y": 56.743851288201405
          },
          "handleType": "smooth"
        },
        {
          "id": "a_mp3x0l5z_7",
          "point": {
            "x": 65.4857984268672,
            "y": 40.571070982010475
          },
          "inHandle": {
            "x": 67.22446950984539,
            "y": 48.71056694805897
          },
          "outHandle": {
            "x": 63.74712734388902,
            "y": 32.43157501596198
          },
          "handleType": "smooth"
        },
        {
          "id": "a_mp3x0l5z_8",
          "point": {
            "x": 61.15299310117754,
            "y": 15.949397643066284
          },
          "inHandle": {
            "x": 62.5972615430741,
            "y": 24.156622089381017
          },
          "outHandle": {
            "x": 59.70872465928099,
            "y": 7.742173196751553
          },
          "handleType": "smooth"
        },
        {
          "id": "a_mp3x0l5z_9",
          "point": {
            "x": 56.82018777548788,
            "y": -8.672275695877914
          },
          "inHandle": {
            "x": 58.041906517832885,
            "y": -0.43211491430138516
          },
          "outHandle": {
            "x": 55.59846903314288,
            "y": -16.912436477454442
          },
          "handleType": "smooth"
        },
        {
          "id": "a_mp3x0l5z_a",
          "point": {
            "x": 53.82268064710752,
            "y": -33.49156704639289
          },
          "inHandle": {
            "x": 54.63917139563358,
            "y": -25.20089267211052
          },
          "outHandle": {
            "x": 53.006189898581454,
            "y": -41.782241420675255
          },
          "handleType": "smooth"
        },
        {
          "id": "a_mp3x0l5z_b",
          "point": {
            "x": 51.921243284331474,
            "y": -58.41632194157213
          },
          "inHandle": {
            "x": 52.53353508821846,
            "y": -50.10601296418263
          },
          "outHandle": {
            "x": 51.30895148044449,
            "y": -66.72663091896163
          },
          "handleType": "smooth"
        },
        {
          "id": "a_mp3x0l5z_c",
          "point": {
            "x": 50.14892982378562,
            "y": -83.35342091072987
          },
          "inHandle": {
            "x": 50.60006320675749,
            "y": -75.03939356298565
          },
          "outHandle": {
            "x": 49.697796440813754,
            "y": -91.66744825847408
          },
          "handleType": "smooth"
        },
        {
          "id": "a_mp3x0l5z_d",
          "point": {
            "x": 49.21444298650027,
            "y": -108.30048602803738
          },
          "inHandle": {
            "x": 49.173752393740635,
            "y": -99.98060831642354
          },
          "outHandle": {
            "x": 49.25513357925991,
            "y": -116.62036373965122
          },
          "handleType": "smooth"
        },
        {
          "id": "a_mp3x0l5z_e",
          "point": {
            "x": 50.393073380343466,
            "y": -133.27268718041296
          },
          "inHandle": {
            "x": 49.715284873088876,
            "y": -124.97854636035765
          },
          "outHandle": {
            "x": 51.070861887598056,
            "y": -141.56682800046826
          },
          "handleType": "smooth"
        },
        {
          "id": "a_mp3x0l5z_f",
          "point": {
            "x": 53.2811740300278,
            "y": -158.06533094836922
          },
          "inHandle": {
            "x": 51.858474925482106,
            "y": -149.88169664783229
          },
          "outHandle": {
            "x": 54.70387313457349,
            "y": -166.24896524890616
          },
          "handleType": "smooth"
        },
        {
          "id": "a_mp3x0l5z_g",
          "point": {
            "x": 58.92926800761762,
            "y": -182.37449298363458
          },
          "inHandle": {
            "x": 56.83368621644652,
            "y": -174.3193603820128
          },
          "outHandle": {
            "x": 61.02484979878872,
            "y": -190.42962558525636
          },
          "handleType": "smooth"
        },
        {
          "id": "a_mp3x0l5z_h",
          "point": {
            "x": 65.8546647770544,
            "y": -206.3961265580998
          },
          "inHandle": {
            "x": 63.99071927857576,
            "y": -198.29170791595146
          },
          "outHandle": {
            "x": 67.71861027553302,
            "y": -214.50054520024815
          },
          "handleType": "smooth"
        },
        {
          "id": "a_mp3x0l5z_i",
          "point": {
            "x": 70.11294099848942,
            "y": -231.00100483652466
          },
          "inHandle": {
            "x": 67.39713204452913,
            "y": -223.6050839518487
          },
          "outHandle": {
            "x": 72.82874995244971,
            "y": -238.3969257212006
          },
          "handleType": "smooth"
        },
        {
          "id": "a_mp3x0l5z_j",
          "point": {
            "x": 82.14951850081614,
            "y": -250.77165186615542
          },
          "inHandle": {
            "x": 76.04831752776545,
            "y": -246.81142025351494
          },
          "outHandle": {
            "x": 88.25071947386684,
            "y": -254.7318834787959
          },
          "handleType": "smooth"
        },
        {
          "id": "a_mp3x0l5z_k",
          "point": {
            "x": 106.72014683679363,
            "y": -254.76239451236756
          },
          "inHandle": {
            "x": 98.49604518536242,
            "y": -253.53825779241257
          },
          "outHandle": {
            "x": 114.94424848822484,
            "y": -255.98653123232256
          },
          "handleType": "smooth"
        },
        {
          "id": "a_mp3x0l5z_l",
          "point": {
            "x": 131.4941284094034,
            "y": -258.1164721858854
          },
          "inHandle": {
            "x": 123.23613455186681,
            "y": -256.9984462947128
          },
          "outHandle": {
            "x": 139.75212226694,
            "y": -259.23449807705805
          },
          "handleType": "smooth"
        },
        {
          "id": "a_mp3x0l5z_m",
          "point": {
            "x": 156.2681099820132,
            "y": -261.4705498594033
          },
          "inHandle": {
            "x": 148.04975438170237,
            "y": -260.11363049236894
          },
          "outHandle": {
            "x": 164.486465582324,
            "y": -262.8274692264377
          },
          "handleType": "smooth"
        },
        {
          "id": "a_mp3x0l5z_n",
          "point": {
            "x": 180.80426201126835,
            "y": -266.2579883880917
          },
          "inHandle": {
            "x": 172.6897769402738,
            "y": -264.39194508928574
          },
          "outHandle": {
            "x": 188.9187470822629,
            "y": -268.12403168689764
          },
          "handleType": "smooth"
        },
        {
          "id": "a_mp3x0l5z_o",
          "point": {
            "x": 204.95502040798053,
            "y": -272.66680965223907
          },
          "inHandle": {
            "x": 196.92070121583743,
            "y": -270.46399913803884
          },
          "outHandle": {
            "x": 212.98933960012363,
            "y": -274.8696201664393
          },
          "handleType": "smooth"
        },
        {
          "id": "a_mp3x0l5z_p",
          "point": {
            "x": 229.01017716412701,
            "y": -279.474851473293
          },
          "inHandle": {
            "x": 220.99179157874485,
            "y": -277.20550419960836
          },
          "outHandle": {
            "x": 237.02856274950918,
            "y": -281.7441987469776
          },
          "handleType": "smooth"
        },
        {
          "id": "a_mp3x0l5z_q",
          "point": {
            "x": 253.06533392027353,
            "y": -286.2828932943469
          },
          "inHandle": {
            "x": 245.04694833489137,
            "y": -284.01354602066226
          },
          "outHandle": {
            "x": 261.0837195056557,
            "y": -288.5522405680315
          },
          "handleType": "smooth"
        },
        {
          "id": "a_mp3x0l5z_r",
          "point": {
            "x": 277.12049067642005,
            "y": -293.09093511540084
          },
          "inHandle": {
            "x": 269.0407056312333,
            "y": -291.12220114302517
          },
          "outHandle": {
            "x": 285.2002757216068,
            "y": -295.0596690877765
          },
          "handleType": "smooth"
        },
        {
          "id": "a_mp3x0l5z_s",
          "point": {
            "x": 301.5440441913937,
            "y": -298.09529712860086
          },
          "inHandle": {
            "x": 293.34041997027765,
            "y": -296.7328828799822
          },
          "outHandle": {
            "x": 309.74766841250977,
            "y": -299.45771137721954
          },
          "handleType": "smooth"
        },
        {
          "id": "a_mp3x0l5z_t",
          "point": {
            "x": 326.3422360031163,
            "y": -301.26542060711284
          },
          "inHandle": {
            "x": 318.1027846811875,
            "y": -300.114601384707
          },
          "outHandle": {
            "x": 334.5816873250451,
            "y": -302.4162398295187
          },
          "handleType": "smooth"
        },
        {
          "id": "a_mp3x0l5z_u",
          "point": {
            "x": 350.9807521229666,
            "y": -305.00021246303595
          },
          "inHandle": {
            "x": 343.076653098288,
            "y": -302.66347173104487
          },
          "outHandle": {
            "x": 358.8848511476452,
            "y": -307.33695319502704
          },
          "handleType": "smooth"
        },
        {
          "id": "a_mp3x0l5z_v",
          "point": {
            "x": 373.766830151188,
            "y": -315.28586499905936
          },
          "inHandle": {
            "x": 366.1714708084475,
            "y": -311.8573141537182
          },
          "outHandle": {
            "x": 381.3621894939285,
            "y": -318.7144158444005
          },
          "handleType": "smooth"
        },
        {
          "id": "a_mp3x0l5z_w",
          "point": {
            "x": 396.5529081794094,
            "y": -325.57151753508276
          },
          "inHandle": {
            "x": 388.95754883666893,
            "y": -322.1429666897416
          },
          "outHandle": {
            "x": 404.1482675221499,
            "y": -329.0000683804239
          },
          "handleType": "smooth"
        },
        {
          "id": "a_mp3x0l5z_x",
          "point": {
            "x": 419.33898620763085,
            "y": -335.85717007110617
          },
          "inHandle": {
            "x": 411.5923313956283,
            "y": -332.8618470308928
          },
          "outHandle": {
            "x": 427.0856410196334,
            "y": -338.8524931113195
          },
          "handleType": "smooth"
        },
        {
          "id": "a_mp3x0l5z_y",
          "point": {
            "x": 443.0328370514247,
            "y": -343.54345577636286
          },
          "inHandle": {
            "x": 435.0446286194538,
            "y": -341.2398107163955
          },
          "outHandle": {
            "x": 451.02104548339554,
            "y": -345.84710083633024
          },
          "handleType": "smooth"
        },
        {
          "id": "a_mp3x0l5z_z",
          "point": {
            "x": 467.268236799456,
            "y": -349.6790404309106
          },
          "inHandle": {
            "x": 459.1155187574964,
            "y": -348.0011861144701
          },
          "outHandle": {
            "x": 475.42095484141566,
            "y": -351.35689474735113
          },
          "handleType": "smooth"
        },
        {
          "id": "a_mp3x0l5z_10",
          "point": {
            "x": 491.9491453031827,
            "y": -353.61058167500613
          },
          "inHandle": {
            "x": 483.71636438373065,
            "y": -352.32881846856765
          },
          "outHandle": {
            "x": 500.1819262226348,
            "y": -354.8923448814446
          },
          "handleType": "smooth"
        },
        {
          "id": "a_mp3x0l5z_11",
          "point": {
            "x": 516.6649223161685,
            "y": -357.36961966954146
          },
          "inHandle": {
            "x": 508.61119270283757,
            "y": -355.42151286678336
          },
          "outHandle": {
            "x": 524.7186519294994,
            "y": -359.31772647229957
          },
          "handleType": "smooth"
        },
        {
          "id": "a_mp3x0l5z_12",
          "point": {
            "x": 540.2715229831683,
            "y": -365.29922249155493
          },
          "inHandle": {
            "x": 532.9544334772074,
            "y": -361.5620170807764
          },
          "outHandle": {
            "x": 547.5886124891292,
            "y": -369.03642790233346
          },
          "handleType": "smooth"
        },
        {
          "id": "a_mp3x0l5z_13",
          "point": {
            "x": 560.5674593519336,
            "y": -379.79285213421275
          },
          "inHandle": {
            "x": 554.4033372125426,
            "y": -374.2919559834087
          },
          "outHandle": {
            "x": 566.7315814913246,
            "y": -385.2937482850168
          },
          "handleType": "smooth"
        },
        {
          "id": "a_mp3x0l5z_14",
          "point": {
            "x": 577.2562558195145,
            "y": -398.3045993963795
          },
          "inHandle": {
            "x": 573.1940505015986,
            "y": -391.32000958140054
          },
          "outHandle": {
            "x": 581.3184611374305,
            "y": -405.28918921135846
          },
          "handleType": "smooth"
        },
        {
          "id": "a_mp3x0l5z_15",
          "point": {
            "x": 584.9406912594295,
            "y": -421.70039102408646
          },
          "inHandle": {
            "x": 584.0951241800469,
            "y": -413.67279806230215
          },
          "outHandle": {
            "x": 585.7862583388121,
            "y": -429.72798398587076
          },
          "handleType": "smooth"
        },
        {
          "id": "a_mp3x0l5z_16",
          "point": {
            "x": 582.3296582958103,
            "y": -446.4701571670855
          },
          "inHandle": {
            "x": 584.3085418829461,
            "y": -438.47171214841967
          },
          "outHandle": {
            "x": 580.3507747086745,
            "y": -454.46860218575137
          },
          "handleType": "smooth"
        },
        {
          "id": "a_mp3x0l5z_17",
          "point": {
            "x": 573.0673897366149,
            "y": -469.69106113608166
          },
          "inHandle": {
            "x": 577.2055474340243,
            "y": -462.7659173707325
          },
          "outHandle": {
            "x": 568.9292320392055,
            "y": -476.6162049014308
          },
          "handleType": "smooth"
        },
        {
          "id": "a_mp3x0l5z_18",
          "point": {
            "x": 557.5007121113541,
            "y": -488.0210197591805
          },
          "inHandle": {
            "x": 563.1711148188626,
            "y": -482.1578685906906
          },
          "outHandle": {
            "x": 551.8303094038456,
            "y": -493.88417092767037
          },
          "handleType": "smooth"
        },
        {
          "id": "a_mp3x0l5z_19",
          "point": {
            "x": 539.0449734915638,
            "y": -504.869968147021
          },
          "inHandle": {
            "x": 543.7929775162828,
            "y": -498.3518848758647
          },
          "outHandle": {
            "x": 534.2969694668449,
            "y": -511.38805141817727
          },
          "handleType": "smooth"
        },
        {
          "id": "a_mp3x0l5z_1a",
          "point": {
            "x": 529.0126879630405,
            "y": -527.1295193861182
          },
          "inHandle": {
            "x": 529.3441439339528,
            "y": -519.5231295624245
          },
          "outHandle": {
            "x": 528.6812319921283,
            "y": -534.7359092098119
          },
          "handleType": "smooth"
        },
        {
          "id": "a_mp3x0l5z_1b",
          "point": {
            "x": 537.0562376660909,
            "y": -550.5083070891831
          },
          "inHandle": {
            "x": 533.3351795766572,
            "y": -543.2074586981498
          },
          "outHandle": {
            "x": 540.7772957555245,
            "y": -557.8091554802163
          },
          "handleType": "smooth"
        },
        {
          "id": "a_mp3x0l5z_1c",
          "point": {
            "x": 551.3390364996425,
            "y": -570.934609732318
          },
          "inHandle": {
            "x": 546.4586654131738,
            "y": -564.1968210879188
          },
          "outHandle": {
            "x": 556.2194075861112,
            "y": -577.6723983767172
          },
          "handleType": "smooth"
        },
        {
          "id": "a_mp3x0l5z_1d",
          "point": {
            "x": 566.3384641849029,
            "y": -590.9350389555782
          },
          "inHandle": {
            "x": 561.3386549564827,
            "y": -584.2682292144915
          },
          "outHandle": {
            "x": 571.3382734133231,
            "y": -597.6018486966649
          },
          "handleType": "smooth"
        },
        {
          "id": "a_mp3x0l5z_1e",
          "point": {
            "x": 581.3378918701634,
            "y": -610.9354681788384
          },
          "inHandle": {
            "x": 576.3380826417432,
            "y": -604.2686584377516
          },
          "outHandle": {
            "x": 586.3377010985836,
            "y": -617.6022779199252
          },
          "handleType": "smooth"
        },
        {
          "id": "a_mp3x0l5z_1f",
          "point": {
            "x": 596.3373195554238,
            "y": -630.9358974020987
          },
          "inHandle": {
            "x": 591.3375103270037,
            "y": -624.269087661012
          },
          "outHandle": {
            "x": 601.337128783844,
            "y": -637.6027071431854
          },
          "handleType": "smooth"
        },
        {
          "id": "a_mp3x0l5z_1g",
          "point": {
            "x": 611.3367472406843,
            "y": -650.9363266253589
          },
          "inHandle": {
            "x": 606.3369380122641,
            "y": -644.2695168842722
          },
          "outHandle": {
            "x": 616.3365564691045,
            "y": -657.6031363664456
          },
          "handleType": "smooth"
        },
        {
          "id": "a_mp3x0l5z_1h",
          "point": {
            "x": 626.3361749259448,
            "y": -670.9367558486191
          },
          "inHandle": {
            "x": 621.3363656975246,
            "y": -664.2699461075324
          },
          "outHandle": {
            "x": 631.335984154365,
            "y": -677.6035655897058
          },
          "handleType": "smooth"
        },
        {
          "id": "a_mp3x0l5z_1i",
          "point": {
            "x": 641.3356026112053,
            "y": -690.9371850718794
          },
          "inHandle": {
            "x": 636.0286043391587,
            "y": -684.7276812529904
          },
          "outHandle": {
            "x": 646.6426008832519,
            "y": -697.1466888907685
          },
          "handleType": "smooth"
        },
        {
          "id": "a_mp3x0l5z_1j",
          "point": {
            "x": 658.1781645582246,
            "y": -708.1937787619536
          },
          "inHandle": {
            "x": 651.7819128182396,
            "y": -706.9864672771845
          },
          "outHandle": {
            "x": 664.5744162982096,
            "y": -709.4010902467227
          },
          "handleType": "smooth"
        },
        {
          "id": "a_mp3x0l5z_1k",
          "point": {
            "x": 679.7131130511157,
            "y": -698.1810539804941
          },
          "inHandle": {
            "x": 675.1864293166868,
            "y": -703.8184685112279
          },
          "outHandle": {
            "x": 684.2397967855445,
            "y": -692.5436394497602
          },
          "handleType": "smooth"
        },
        {
          "id": "a_mp3x0l5z_1l",
          "point": {
            "x": 685.3382669647976,
            "y": -674.3692915775506
          },
          "inHandle": {
            "x": 682.9352379818049,
            "y": -682.1435907679376
          },
          "outHandle": {
            "x": 687.7412959477904,
            "y": -666.5949923871636
          },
          "handleType": "smooth"
        },
        {
          "id": "a_mp3x0l5z_1m",
          "point": {
            "x": 694.1312869490724,
            "y": -651.5352588381724
          },
          "inHandle": {
            "x": 690.3757853989607,
            "y": -658.8209539077435
          },
          "outHandle": {
            "x": 697.8867884991841,
            "y": -644.2495637686012
          },
          "handleType": "smooth"
        },
        {
          "id": "a_mp3x0l5z_1n",
          "point": {
            "x": 707.8712762654683,
            "y": -630.6551211601236
          },
          "inHandle": {
            "x": 703.4080465835643,
            "y": -637.5520019685337
          },
          "outHandle": {
            "x": 712.3345059473722,
            "y": -623.7582403517135
          },
          "handleType": "smooth"
        },
        {
          "id": "a_mp3x0l5z_1o",
          "point": {
            "x": 720.9106650404963,
            "y": -610.1539739877121
          },
          "inHandle": {
            "x": 716.4004579491134,
            "y": -611.3572895421286
          },
          "outHandle": {
            "x": 725.4208721318792,
            "y": -608.9506584332956
          },
          "handleType": "smooth"
        },
        {
          "id": "a_mp3x0l5z_1p",
          "point": {
            "x": 734.9325188137655,
            "y": -623.4352278336247
          },
          "inHandle": {
            "x": 735.3145633896102,
            "y": -618.101637537929
          },
          "outHandle": {
            "x": 734.5504742379208,
            "y": -628.7688181293204
          },
          "handleType": "smooth"
        },
        {
          "id": "a_mp3x0l5z_1q",
          "point": {
            "x": 718.618397585428,
            "y": -642.1555157618859
          },
          "inHandle": {
            "x": 723.8391448428839,
            "y": -635.7034304294035
          },
          "outHandle": {
            "x": 713.3976503279722,
            "y": -648.6076010943683
          },
          "handleType": "smooth"
        },
        {
          "id": "a_mp3x0l5z_1r",
          "point": {
            "x": 703.6080352690303,
            "y": -662.1477398285192
          },
          "inHandle": {
            "x": 705.9035051380766,
            "y": -655.0594922927082
          },
          "outHandle": {
            "x": 701.312565399984,
            "y": -669.2359873643302
          },
          "handleType": "smooth"
        },
        {
          "id": "a_mp3x0l5z_1s",
          "point": {
            "x": 704.8455783711503,
            "y": -684.685000976752
          },
          "inHandle": {
            "x": 700.7726747964216,
            "y": -679.4893468741543
          },
          "outHandle": {
            "x": 708.918481945879,
            "y": -689.8806550793497
          },
          "handleType": "smooth"
        },
        {
          "id": "a_mp3x0l5z_1t",
          "point": {
            "x": 728.0454567174025,
            "y": -693.3216644441055
          },
          "inHandle": {
            "x": 720.263067929736,
            "y": -690.4719829679215
          },
          "outHandle": {
            "x": 735.827845505069,
            "y": -696.1713459202896
          },
          "handleType": "smooth"
        },
        {
          "id": "a_mp3x0l5z_1u",
          "point": {
            "x": 751.5399110971496,
            "y": -701.7830898338566
          },
          "inHandle": {
            "x": 743.5680768984544,
            "y": -699.6532203648061
          },
          "outHandle": {
            "x": 759.5117452958448,
            "y": -703.9129593029071
          },
          "handleType": "smooth"
        },
        {
          "id": "a_mp3x0l5z_1v",
          "point": {
            "x": 775.8764619095734,
            "y": -706.1008812584088
          },
          "inHandle": {
            "x": 770.3100141090422,
            "y": -708.7371202781321
          },
          "outHandle": {
            "x": 781.4429097101047,
            "y": -703.4646422386854
          },
          "handleType": "smooth"
        },
        {
          "id": "a_mp3x0l5z_1w",
          "point": {
            "x": 784.9385979003367,
            "y": -685.9656557155163
          },
          "inHandle": {
            "x": 783.6663627070172,
            "y": -693.4813835591392
          },
          "outHandle": {
            "x": 786.2108330936562,
            "y": -678.4499278718934
          },
          "handleType": "smooth"
        },
        {
          "id": "a_mp3x0l5z_1x",
          "point": {
            "x": 783.5098730694901,
            "y": -661.0065141966714
          },
          "inHandle": {
            "x": 783.9861146797723,
            "y": -669.3262280362864
          },
          "outHandle": {
            "x": 783.033631459208,
            "y": -652.6868003570565
          },
          "handleType": "smooth"
        },
        {
          "id": "a_mp3x0l5z_1y",
          "point": {
            "x": 782.0811482386434,
            "y": -636.0473726778267
          },
          "inHandle": {
            "x": 782.5573898489256,
            "y": -644.3670865174416
          },
          "outHandle": {
            "x": 781.6049066283613,
            "y": -627.7276588382118
          },
          "handleType": "smooth"
        },
        {
          "id": "a_mp3x0l5z_1z",
          "point": {
            "x": 780.6524234077968,
            "y": -611.0882311589819
          },
          "inHandle": {
            "x": 781.32685238639,
            "y": -619.3818216094385
          },
          "outHandle": {
            "x": 779.9779944292037,
            "y": -602.7946407085253
          },
          "handleType": "smooth"
        },
        {
          "id": "a_mp3x0l5z_20",
          "point": {
            "x": 778.0345743670846,
            "y": -586.2858299750876
          },
          "inHandle": {
            "x": 779.3188015090631,
            "y": -594.4990419692077
          },
          "outHandle": {
            "x": 776.7503472251061,
            "y": -578.0726179809675
          },
          "handleType": "smooth"
        },
        {
          "id": "a_mp3x0l5z_21",
          "point": {
            "x": 772.9470605559262,
            "y": -561.8089591942612
          },
          "inHandle": {
            "x": 774.8492529252367,
            "y": -569.911724107144
          },
          "outHandle": {
            "x": 771.0448681866158,
            "y": -553.7061942813784
          },
          "handleType": "smooth"
        },
        {
          "id": "a_mp3x0l5z_22",
          "point": {
            "x": 766.621420151222,
            "y": -537.6692404977912
          },
          "inHandle": {
            "x": 769.0842102144961,
            "y": -545.6097054427165
          },
          "outHandle": {
            "x": 764.1586300879478,
            "y": -529.7287755528658
          },
          "handleType": "smooth"
        },
        {
          "id": "a_mp3x0l5z_23",
          "point": {
            "x": 758.1703201762816,
            "y": -514.1661695247094
          },
          "inHandle": {
            "x": 761.3846719408498,
            "y": -521.8383541048005
          },
          "outHandle": {
            "x": 754.9559684117135,
            "y": -506.4939849446183
          },
          "handleType": "smooth"
        },
        {
          "id": "a_mp3x0l5z_24",
          "point": {
            "x": 747.3353095638131,
            "y": -491.6361330172447
          },
          "inHandle": {
            "x": 751.0764931876572,
            "y": -499.07178646667853
          },
          "outHandle": {
            "x": 743.594125939969,
            "y": -484.2004795678108
          },
          "handleType": "smooth"
        },
        {
          "id": "a_mp3x0l5z_25",
          "point": {
            "x": 735.7232184332166,
            "y": -469.5522488281064
          },
          "inHandle": {
            "x": 739.9909534279041,
            "y": -476.6855885412679
          },
          "outHandle": {
            "x": 731.4554834385292,
            "y": -462.41890911494494
          },
          "handleType": "smooth"
        },
        {
          "id": "a_mp3x0l5z_26",
          "point": {
            "x": 721.7288995956886,
            "y": -448.83609473827573
          },
          "inHandle": {
            "x": 726.554862566953,
            "y": -455.6146112637075
          },
          "outHandle": {
            "x": 716.9029366244242,
            "y": -442.05757821284396
          },
          "handleType": "smooth"
        },
        {
          "id": "a_mp3x0l5z_27",
          "point": {
            "x": 706.7674406056299,
            "y": -428.88114967551576
          },
          "inHandle": {
            "x": 712.0690262953002,
            "y": -435.285316831021
          },
          "outHandle": {
            "x": 701.4658549159595,
            "y": -422.4769825200105
          },
          "handleType": "smooth"
        },
        {
          "id": "a_mp3x0l5z_28",
          "point": {
            "x": 689.9193854576664,
            "y": -410.41109180524415
          },
          "inHandle": {
            "x": 695.6966507501829,
            "y": -416.4002575250372
          },
          "outHandle": {
            "x": 684.1421201651499,
            "y": -404.4219260854511
          },
          "handleType": "smooth"
        },
        {
          "id": "a_mp3x0l5z_29",
          "point": {
            "x": 672.1038488505311,
            "y": -392.9461553567575
          },
          "inHandle": {
            "x": 678.2563294186457,
            "y": -398.5455080132517
          },
          "outHandle": {
            "x": 665.9513682824165,
            "y": -387.3468027002633
          },
          "handleType": "smooth"
        },
        {
          "id": "a_mp3x0l5z_2a",
          "point": {
            "x": 653.0045020489789,
            "y": -376.8149758662789
          },
          "inHandle": {
            "x": 659.6744149066124,
            "y": -381.7801898165746
          },
          "outHandle": {
            "x": 646.3345891913455,
            "y": -371.84976191598327
          },
          "handleType": "smooth"
        },
        {
          "id": "a_mp3x0l5z_2b",
          "point": {
            "x": 632.0843717047304,
            "y": -363.15487165498365
          },
          "inHandle": {
            "x": 639.0818961827277,
            "y": -367.67546769366555
          },
          "outHandle": {
            "x": 625.0868472267331,
            "y": -358.63427561630175
          },
          "handleType": "smooth"
        },
        {
          "id": "a_mp3x0l5z_2c",
          "point": {
            "x": 611.0193551809951,
            "y": -349.69139963418746
          },
          "inHandle": {
            "x": 618.2271790801726,
            "y": -353.85397339472485
          },
          "outHandle": {
            "x": 603.8115312818177,
            "y": -345.5288258736501
          },
          "handleType": "smooth"
        },
        {
          "id": "a_mp3x0l5z_2d",
          "point": {
            "x": 588.8374283096659,
            "y": -338.1794290917594
          },
          "inHandle": {
            "x": 596.2474811591406,
            "y": -341.98866196300855
          },
          "outHandle": {
            "x": 581.4273754601912,
            "y": -334.37019622051025
          },
          "handleType": "smooth"
        },
        {
          "id": "a_mp3x0l5z_2e",
          "point": {
            "x": 566.5590380841467,
            "y": -326.83600240669256
          },
          "inHandle": {
            "x": 573.9851681593198,
            "y": -330.6171446350482
          },
          "outHandle": {
            "x": 559.1329080089736,
            "y": -323.0548601783369
          },
          "handleType": "smooth"
        },
        {
          "id": "a_mp3x0l5z_2f",
          "point": {
            "x": 544.2806478586274,
            "y": -315.49257572162566
          },
          "inHandle": {
            "x": 551.8938153986832,
            "y": -318.8275988355723
          },
          "outHandle": {
            "x": 536.6674803185716,
            "y": -312.157552607679
          },
          "handleType": "smooth"
        },
        {
          "id": "a_mp3x0l5z_2g",
          "point": {
            "x": 520.8800328438119,
            "y": -306.82586372301284
          },
          "inHandle": {
            "x": 528.7499800602887,
            "y": -309.5292924630829
          },
          "outHandle": {
            "x": 513.0100856273351,
            "y": -304.12243498294276
          },
          "handleType": "smooth"
        },
        {
          "id": "a_mp3x0l5z_2h",
          "point": {
            "x": 497.06096455976626,
            "y": -299.272003281205
          },
          "inHandle": {
            "x": 505.07840613297367,
            "y": -301.5144059055181
          },
          "outHandle": {
            "x": 489.04352298655886,
            "y": -297.0296006568919
          },
          "handleType": "smooth"
        },
        {
          "id": "a_mp3x0l5z_2i",
          "point": {
            "x": 472.77538340456744,
            "y": -293.37144797713415
          },
          "inHandle": {
            "x": 480.9287987502842,
            "y": -295.06435653668245
          },
          "outHandle": {
            "x": 464.62196805885065,
            "y": -291.67853941758585
          },
          "handleType": "smooth"
        },
        {
          "id": "a_mp3x0l5z_2j",
          "point": {
            "x": 448.14047248546547,
            "y": -289.11455192391537
          },
          "inHandle": {
            "x": 456.35210945849946,
            "y": -290.5335172749883
          },
          "outHandle": {
            "x": 439.9288355124315,
            "y": -287.69558657284244
          },
          "handleType": "smooth"
        },
        {
          "id": "a_mp3x0l5z_2k",
          "point": {
            "x": 423.50556156636344,
            "y": -284.85765587069665
          },
          "inHandle": {
            "x": 431.71719853939743,
            "y": -286.2766212217696
          },
          "outHandle": {
            "x": 415.29392459332945,
            "y": -283.4386905196237
          },
          "handleType": "smooth"
        },
        {
          "id": "a_mp3x0l5z_2l",
          "point": {
            "x": 398.87065064726147,
            "y": -280.60075981747786
          },
          "inHandle": {
            "x": 404.48011760382224,
            "y": -284.48721849192583
          },
          "outHandle": {
            "x": 393.2611836907007,
            "y": -276.7143011430299
          },
          "handleType": "smooth"
        },
        {
          "id": "a_mp3x0l5z_2m",
          "point": {
            "x": 389.8487598269987,
            "y": -261.5389038240088
          },
          "inHandle": {
            "x": 394.98667293749827,
            "y": -265.9966844636746
          },
          "outHandle": {
            "x": 384.7108467164991,
            "y": -257.08112318434297
          },
          "handleType": "smooth"
        },
        {
          "id": "a_mp3x0l5z_2n",
          "point": {
            "x": 368.04317198426384,
            "y": -253.85407597948293
          },
          "inHandle": {
            "x": 375.5645190307529,
            "y": -254.00643419020923
          },
          "outHandle": {
            "x": 360.5218249377748,
            "y": -253.70171776875662
          },
          "handleType": "smooth"
        },
        {
          "id": "a_mp3x0l5z_2o",
          "point": {
            "x": 344.72067754806443,
            "y": -260.62475455965097
          },
          "inHandle": {
            "x": 352.7344822731965,
            "y": -260.0718722113403
          },
          "outHandle": {
            "x": 336.7068728229324,
            "y": -261.17763690796164
          },
          "handleType": "smooth"
        },
        {
          "id": "a_mp3x0l5z_2p",
          "point": {
            "x": 319.9603436334717,
            "y": -257.1713700693471
          },
          "inHandle": {
            "x": 328.2137882716693,
            "y": -258.32249823278175
          },
          "outHandle": {
            "x": 311.7068989952742,
            "y": -256.0202419059125
          },
          "handleType": "smooth"
        },
        {
          "id": "a_mp3x0l5z_2q",
          "point": {
            "x": 295.2000097188791,
            "y": -253.7179855790433
          },
          "inHandle": {
            "x": 303.4534543570766,
            "y": -254.8691137424779
          },
          "outHandle": {
            "x": 286.9465650806815,
            "y": -252.5668574156087
          },
          "handleType": "smooth"
        },
        {
          "id": "a_mp3x0l5z_2r",
          "point": {
            "x": 270.43967580428637,
            "y": -250.26460108873945
          },
          "inHandle": {
            "x": 278.6931204424839,
            "y": -251.41572925217406
          },
          "outHandle": {
            "x": 262.1862311660888,
            "y": -249.11347292530485
          },
          "handleType": "smooth"
        },
        {
          "id": "a_mp3x0l5z_2s",
          "point": {
            "x": 245.67934188969366,
            "y": -246.8112165984356
          },
          "inHandle": {
            "x": 253.9327865278912,
            "y": -247.9623447618702
          },
          "outHandle": {
            "x": 237.4258972514961,
            "y": -245.660088435001
          },
          "handleType": "smooth"
        },
        {
          "id": "a_mp3x0l5z_2t",
          "point": {
            "x": 220.919007975101,
            "y": -243.35783210813176
          },
          "inHandle": {
            "x": 229.17245261329856,
            "y": -244.50896027156637
          },
          "outHandle": {
            "x": 212.66556333690346,
            "y": -242.20670394469715
          },
          "handleType": "smooth"
        },
        {
          "id": "a_mp3x0l5z_2u",
          "point": {
            "x": 196.1586740605083,
            "y": -239.9044476178279
          },
          "inHandle": {
            "x": 204.41211869870588,
            "y": -241.05557578126252
          },
          "outHandle": {
            "x": 187.90522942231073,
            "y": -238.7533194543933
          },
          "handleType": "smooth"
        },
        {
          "id": "a_mp3x0l5z_2v",
          "point": {
            "x": 171.3983401459156,
            "y": -236.45106312752404
          },
          "inHandle": {
            "x": 179.65178478411315,
            "y": -237.60219129095864
          },
          "outHandle": {
            "x": 163.14489550771805,
            "y": -235.29993496408943
          },
          "handleType": "smooth"
        },
        {
          "id": "a_mp3x0l5z_2w",
          "point": {
            "x": 146.63800623132295,
            "y": -232.99767863722022
          },
          "inHandle": {
            "x": 154.37436934789403,
            "y": -235.2026656416441
          },
          "outHandle": {
            "x": 138.90164311475186,
            "y": -230.79269163279633
          },
          "handleType": "smooth"
        },
        {
          "id": "a_mp3x0l5z_2x",
          "point": {
            "x": 124.98016144648905,
            "y": -223.2211411009807
          },
          "inHandle": {
            "x": 130.53626479577457,
            "y": -228.5346371290287
          },
          "outHandle": {
            "x": 119.42405809720351,
            "y": -217.9076450729327
          },
          "handleType": "smooth"
        },
        {
          "id": "a_mp3x0l5z_2y",
          "point": {
            "x": 113.30138613560976,
            "y": -201.11670246893223
          },
          "inHandle": {
            "x": 116.78487717675814,
            "y": -208.66287658063624
          },
          "outHandle": {
            "x": 109.81789509446138,
            "y": -193.57052835722823
          },
          "handleType": "smooth"
        },
        {
          "id": "a_mp3x0l5z_2z",
          "point": {
            "x": 104.07921519959875,
            "y": -177.94409643075664
          },
          "inHandle": {
            "x": 106.68122366547954,
            "y": -185.82616848252724
          },
          "outHandle": {
            "x": 101.47720673371796,
            "y": -170.06202437898605
          },
          "handleType": "smooth"
        },
        {
          "id": "a_mp3x0l5z_30",
          "point": {
            "x": 97.68933534032504,
            "y": -153.8242701583087
          },
          "inHandle": {
            "x": 99.23532472076126,
            "y": -161.97036257507193
          },
          "outHandle": {
            "x": 96.14334595988883,
            "y": -145.67817774154548
          },
          "handleType": "smooth"
        },
        {
          "id": "a_mp3x0l5z_31",
          "point": {
            "x": 94.80327891698151,
            "y": -129.06754193017727
          },
          "inHandle": {
            "x": 95.33972951684756,
            "y": -137.35524075011287
          },
          "outHandle": {
            "x": 94.26682831711547,
            "y": -120.77984311024166
          },
          "handleType": "smooth"
        },
        {
          "id": "a_mp3x0l5z_32",
          "point": {
            "x": 94.47063174112881,
            "y": -104.09807723869504
          },
          "inHandle": {
            "x": 93.50659012615944,
            "y": -112.23642701317405
          },
          "outHandle": {
            "x": 95.43467335609819,
            "y": -95.95972746421603
          },
          "handleType": "smooth"
        },
        {
          "id": "a_mp3x0l5z_33",
          "point": {
            "x": 100.58752860679772,
            "y": -80.23744328330325
          },
          "inHandle": {
            "x": 96.5461168454965,
            "y": -87.0271380266179
          },
          "outHandle": {
            "x": 104.62894036809894,
            "y": -73.4477485399886
          },
          "handleType": "smooth"
        },
        {
          "id": "a_mp3x0l5z_34",
          "point": {
            "x": 118.71910230893609,
            "y": -63.35990877880708
          },
          "inHandle": {
            "x": 113.75955447160011,
            "y": -69.64703338504926
          },
          "outHandle": {
            "x": 123.67865014627206,
            "y": -57.072784172564916
          },
          "handleType": "smooth"
        },
        {
          "id": "a_mp3x0l5z_35",
          "point": {
            "x": 130.34481563081354,
            "y": -42.514695645850246
          },
          "inHandle": {
            "x": 127.71789545130531,
            "y": -50.094456041366406
          },
          "outHandle": {
            "x": 132.97173581032177,
            "y": -34.934935250334085
          },
          "handleType": "smooth"
        },
        {
          "id": "a_mp3x0l5z_36",
          "point": {
            "x": 134.4806233859855,
            "y": -17.88134640571013
          },
          "inHandle": {
            "x": 132.98426049965926,
            "y": -26.074662273383492
          },
          "outHandle": {
            "x": 135.97698627231173,
            "y": -9.688030538036767
          },
          "handleType": "smooth"
        },
        {
          "id": "a_mp3x0l5z_37",
          "point": {
            "x": 139.32299294877103,
            "y": 6.64519956018993
          },
          "inHandle": {
            "x": 137.70886976117586,
            "y": -1.5303157617767553
          },
          "outHandle": {
            "x": 140.9371161363662,
            "y": 14.820714882156615
          },
          "handleType": "smooth"
        },
        {
          "id": "a_mp3x0l5z_38",
          "point": {
            "x": 144.16536251155657,
            "y": 31.17174552608998
          },
          "inHandle": {
            "x": 142.5512393239614,
            "y": 22.996230204123293
          },
          "outHandle": {
            "x": 145.77948569915173,
            "y": 39.34726084805666
          },
          "handleType": "smooth"
        },
        {
          "id": "a_mp3x0l5z_39",
          "point": {
            "x": 149.0077320743421,
            "y": 55.698291491990034
          },
          "inHandle": {
            "x": 149.24886984953014,
            "y": 48.008657347780584
          },
          "outHandle": {
            "x": 148.76659429915406,
            "y": 63.38792563619948
          },
          "handleType": "smooth"
        },
        {
          "id": "a_mp3x0l5z_3a",
          "point": {
            "x": 142.71853586042837,
            "y": 77.30955039134669
          },
          "inHandle": {
            "x": 145.8957138314552,
            "y": 70.71674953998314
          },
          "outHandle": {
            "x": 139.54135788940155,
            "y": 83.90235124271024
          },
          "handleType": "smooth"
        },
        {
          "id": "a_mp3x0l5z_3b",
          "point": {
            "x": 129.9446642481811,
            "y": 95.25509660017134
          },
          "inHandle": {
            "x": 130.9055838995665,
            "y": 88.28423340071946
          },
          "outHandle": {
            "x": 128.98374459679573,
            "y": 102.22595979962323
          },
          "handleType": "smooth"
        },
        {
          "id": "a_mp3x0l5z_3c",
          "point": {
            "x": 136.9530179521161,
            "y": 119.13472958805802
          },
          "inHandle": {
            "x": 134.26630822566915,
            "y": 111.28321698618237
          },
          "outHandle": {
            "x": 139.63972767856308,
            "y": 126.98624218993368
          },
          "handleType": "smooth"
        },
        {
          "id": "a_mp3x0l5z_3d",
          "point": {
            "x": 146.06492260686292,
            "y": 142.36417221142526
          },
          "inHandle": {
            "x": 142.6679954272081,
            "y": 134.77756753574778
          },
          "outHandle": {
            "x": 149.46184978651775,
            "y": 149.95077688710273
          },
          "handleType": "smooth"
        },
        {
          "id": "a_mp3x0l5z_3e",
          "point": {
            "x": 157.33458103004511,
            "y": 164.6543576421229
          },
          "inHandle": {
            "x": 152.98568774369022,
            "y": 157.59717799299537
          },
          "outHandle": {
            "x": 161.6834743164,
            "y": 171.71153729125044
          },
          "handleType": "smooth"
        },
        {
          "id": "a_mp3x0l5z_3f",
          "point": {
            "x": 172.15828232499223,
            "y": 184.70725010619046
          },
          "inHandle": {
            "x": 166.66722821651092,
            "y": 178.51447127043218
          },
          "outHandle": {
            "x": 177.64933643347354,
            "y": 190.90002894194873
          },
          "handleType": "smooth"
        },
        {
          "id": "a_mp3x0l5z_3g",
          "point": {
            "x": 190.28090568093288,
            "y": 201.81103065667253
          },
          "inHandle": {
            "x": 183.64814742608536,
            "y": 196.9020969089328
          },
          "outHandle": {
            "x": 196.9136639357804,
            "y": 206.71996440441225
          },
          "handleType": "smooth"
        },
        {
          "id": "a_mp3x0l5z_3h",
          "point": {
            "x": 211.95483185407736,
            "y": 214.1608525926288
          },
          "inHandle": {
            "x": 205.1464129711105,
            "y": 209.7163126430814
          },
          "outHandle": {
            "x": 218.76325073704422,
            "y": 218.6053925421762
          },
          "handleType": "smooth"
        },
        {
          "id": "a_mp3x0l5z_3i",
          "point": {
            "x": 231.131418978734,
            "y": 228.47827035395684
          },
          "inHandle": {
            "x": 229.45882777246842,
            "y": 222.92250725292365
          },
          "outHandle": {
            "x": 232.80401018499956,
            "y": 234.03403345499004
          },
          "handleType": "smooth"
        },
        {
          "id": "a_mp3x0l5z_3j",
          "point": {
            "x": 221.99037909167075,
            "y": 247.49543119882796
          },
          "inHandle": {
            "x": 227.51725124319051,
            "y": 243.17083913124986
          },
          "outHandle": {
            "x": 216.46350694015098,
            "y": 251.82002326640605
          },
          "handleType": "smooth"
        },
        {
          "id": "a_mp3x0l5z_3k",
          "point": {
            "x": 197.97018606961535,
            "y": 254.4258227594255
          },
          "inHandle": {
            "x": 206.0788587047834,
            "y": 252.6182896595477
          },
          "outHandle": {
            "x": 189.8615134344473,
            "y": 256.2333558593033
          },
          "handleType": "smooth"
        },
        {
          "id": "a_mp3x0l5z_3l",
          "point": {
            "x": 173.33834328066231,
            "y": 258.3406297980946
          },
          "inHandle": {
            "x": 181.3487820208771,
            "y": 258.6787306878535
          },
          "outHandle": {
            "x": 165.32790454044752,
            "y": 258.0025289083357
          },
          "handleType": "smooth"
        },
        {
          "id": "a_mp3x0l5z_3m",
          "point": {
            "x": 149.90755362832658,
            "y": 252.3972174208722
          },
          "inHandle": {
            "x": 155.02438468356655,
            "y": 257.3105777374566
          },
          "outHandle": {
            "x": 144.7907225730866,
            "y": 247.48385710428784
          },
          "handleType": "smooth"
        },
        {
          "id": "a_mp3x0l5z_3n",
          "point": {
            "x": 142.63735694922255,
            "y": 228.86046789858838
          },
          "inHandle": {
            "x": 142.63735694922255,
            "y": 228.86046789858838
          },
          "outHandle": {
            "x": 142.63735694922255,
            "y": 228.86046789858838
          },
          "handleType": "corner"
        }
      ],
      "closed": true,
      "stroke": "#e5e7eb",
      "strokeWidth": 1.5,
      "fill": "none"
    }
  ],
  "checkpoints": [
    {
      "id": "f1_monaco_checkpoint_0",
      "kind": "start-finish",
      "pathId": "f1_monaco_path_0",
      "segmentIndex": 0,
      "t": 0
    },
    {
      "id": "f1_monaco_checkpoint_1",
      "kind": "sector",
      "pathId": "f1_monaco_path_0",
      "segmentIndex": 43,
      "t": 0.20178281799440745
    },
    {
      "id": "f1_monaco_checkpoint_2",
      "kind": "sector",
      "pathId": "f1_monaco_path_0",
      "segmentIndex": 86,
      "t": 0.9747655870884951
    }
  ],
  "raceDirection": "forward",
  "pitBoxAreas": []
}