{
  "id": "f1_zandvoort",
  "name": "Circuit Zandvoort",
  "trackLength": 4408,
  "turns": 14,
  "paths": [
    {
      "id": "f1_zandvoort_path_0",
      "anchors": [
        {
          "id": "a_mp3ssu4q_0",
          "point": {
            "x": 537.2300480327885,
            "y": 92.91992399961615
          },
          "inHandle": {
            "x": 537.2300480327885,
            "y": 92.91992399961615
          },
          "outHandle": {
            "x": 537.2300480327885,
            "y": 92.91992399961615
          },
          "handleType": "corner"
        },
        {
          "id": "a_mp3ssu4q_1",
          "point": {
            "x": 517.7915113465085,
            "y": 79.10868594062049
          },
          "inHandle": {
            "x": 520.9571684882192,
            "y": 85.34305089316277
          },
          "outHandle": {
            "x": 514.6258542047979,
            "y": 72.87432098807821
          },
          "handleType": "smooth"
        },
        {
          "id": "a_mp3ssu4q_2",
          "point": {
            "x": 518.2361051825246,
            "y": 55.513734284362435
          },
          "inHandle": {
            "x": 515.3169576499904,
            "y": 62.46740547867697
          },
          "outHandle": {
            "x": 521.1552527150589,
            "y": 48.5600630900479
          },
          "handleType": "smooth"
        },
        {
          "id": "a_mp3ssu4q_3",
          "point": {
            "x": 535.3063965417139,
            "y": 37.38665877473325
          },
          "inHandle": {
            "x": 529.4599581246769,
            "y": 43.29795394726152
          },
          "outHandle": {
            "x": 541.1528349587509,
            "y": 31.475363602204975
          },
          "handleType": "smooth"
        },
        {
          "id": "a_mp3ssu4q_4",
          "point": {
            "x": 553.314735684747,
            "y": 20.045963249192802
          },
          "inHandle": {
            "x": 547.8598329627362,
            "y": 26.252442363739263
          },
          "outHandle": {
            "x": 558.7696384067578,
            "y": 13.83948413464634
          },
          "handleType": "smooth"
        },
        {
          "id": "a_mp3ssu4q_5",
          "point": {
            "x": 568.0358128737789,
            "y": 0.14778408745447358
          },
          "inHandle": {
            "x": 569.057485641106,
            "y": 2.1602398844738704
          },
          "outHandle": {
            "x": 567.0141401064518,
            "y": -1.8646717095649232
          },
          "handleType": "smooth"
        },
        {
          "id": "a_mp3ssu4q_6",
          "point": {
            "x": 547.1846990807842,
            "y": 7.971228467076422
          },
          "inHandle": {
            "x": 554.3411040757783,
            "y": 4.73581436195005
          },
          "outHandle": {
            "x": 540.0282940857901,
            "y": 11.206642572202794
          },
          "handleType": "smooth"
        },
        {
          "id": "a_mp3ssu4q_7",
          "point": {
            "x": 525.0973829038147,
            "y": 19.56026871821271
          },
          "inHandle": {
            "x": 532.3557147683804,
            "y": 15.492087663650032
          },
          "outHandle": {
            "x": 517.8390510392491,
            "y": 23.62844977277539
          },
          "handleType": "smooth"
        },
        {
          "id": "a_mp3ssu4q_8",
          "point": {
            "x": 503.6347078933905,
            "y": 32.380314794452495
          },
          "inHandle": {
            "x": 510.7889328968653,
            "y": 28.106966102372567
          },
          "outHandle": {
            "x": 496.4804828899157,
            "y": 36.65366348653242
          },
          "handleType": "smooth"
        },
        {
          "id": "a_mp3ssu4q_9",
          "point": {
            "x": 482.1720328829662,
            "y": 45.20036087069228
          },
          "inHandle": {
            "x": 489.47774777070015,
            "y": 41.23074993880278
          },
          "outHandle": {
            "x": 474.8663179952323,
            "y": 49.16997180258178
          },
          "handleType": "smooth"
        },
        {
          "id": "a_mp3ssu4q_a",
          "point": {
            "x": 459.80041856698693,
            "y": 56.19798038578947
          },
          "inHandle": {
            "x": 467.42756844417875,
            "y": 52.923848042304456
          },
          "outHandle": {
            "x": 452.1732686897951,
            "y": 59.472112729274485
          },
          "handleType": "smooth"
        },
        {
          "id": "a_mp3ssu4q_b",
          "point": {
            "x": 436.4091336198152,
            "y": 64.84515493160237
          },
          "inHandle": {
            "x": 444.4050430684342,
            "y": 62.69794471179566
          },
          "outHandle": {
            "x": 428.41322417119613,
            "y": 66.99236515140907
          },
          "handleType": "smooth"
        },
        {
          "id": "a_mp3ssu4q_c",
          "point": {
            "x": 411.8249618752728,
            "y": 69.08124170462972
          },
          "inHandle": {
            "x": 420.0808824369092,
            "y": 68.37372225362616
          },
          "outHandle": {
            "x": 403.5690413136364,
            "y": 69.78876115563328
          },
          "handleType": "smooth"
        },
        {
          "id": "a_mp3ssu4q_d",
          "point": {
            "x": 386.8736102499968,
            "y": 69.09027163762372
          },
          "inHandle": {
            "x": 395.1473825191151,
            "y": 69.69472143641141
          },
          "outHandle": {
            "x": 378.5998379808784,
            "y": 68.48582183883602
          },
          "handleType": "smooth"
        },
        {
          "id": "a_mp3ssu4q_e",
          "point": {
            "x": 362.18232826056277,
            "y": 65.45454291190349
          },
          "inHandle": {
            "x": 370.3720449030246,
            "y": 66.93201166785519
          },
          "outHandle": {
            "x": 353.99261161810097,
            "y": 63.977074155951776
          },
          "handleType": "smooth"
        },
        {
          "id": "a_mp3ssu4q_f",
          "point": {
            "x": 337.7353103952259,
            "y": 60.22545910191345
          },
          "inHandle": {
            "x": 345.88431635033817,
            "y": 61.9684870385768
          },
          "outHandle": {
            "x": 329.5863044401136,
            "y": 58.482431165250105
          },
          "handleType": "smooth"
        },
        {
          "id": "a_mp3ssu4q_g",
          "point": {
            "x": 313.288292529889,
            "y": 54.996375291923414
          },
          "inHandle": {
            "x": 321.4372984850013,
            "y": 56.73940322858676
          },
          "outHandle": {
            "x": 305.13928657477675,
            "y": 53.25334735526007
          },
          "handleType": "smooth"
        },
        {
          "id": "a_mp3ssu4q_h",
          "point": {
            "x": 288.84127466455215,
            "y": 49.767291481933384
          },
          "inHandle": {
            "x": 297.04979081760007,
            "y": 51.15779428005689
          },
          "outHandle": {
            "x": 280.6327585115042,
            "y": 48.37678868380988
          },
          "handleType": "smooth"
        },
        {
          "id": "a_mp3ssu4q_i",
          "point": {
            "x": 264.0371956116016,
            "y": 46.65335850318237
          },
          "inHandle": {
            "x": 272.3341138877637,
            "y": 47.31224618795079
          },
          "outHandle": {
            "x": 255.7402773354395,
            "y": 45.994470818413944
          },
          "handleType": "smooth"
        },
        {
          "id": "a_mp3ssu4q_j",
          "point": {
            "x": 239.05976500757947,
            "y": 45.813965373322844
          },
          "inHandle": {
            "x": 247.37908796245353,
            "y": 45.72669070494078
          },
          "outHandle": {
            "x": 230.74044205270542,
            "y": 45.90124004170491
          },
          "handleType": "smooth"
        },
        {
          "id": "a_mp3ssu4q_k",
          "point": {
            "x": 214.12125788235718,
            "y": 47.177006513474765
          },
          "inHandle": {
            "x": 222.39458700323488,
            "y": 46.34726002208158
          },
          "outHandle": {
            "x": 205.8479287614795,
            "y": 48.00675300486795
          },
          "handleType": "smooth"
        },
        {
          "id": "a_mp3ssu4q_l",
          "point": {
            "x": 189.41979028231327,
            "y": 50.792444321681984
          },
          "inHandle": {
            "x": 197.56477272719587,
            "y": 49.144043780563976
          },
          "outHandle": {
            "x": 181.27480783743067,
            "y": 52.44084486279999
          },
          "handleType": "smooth"
        },
        {
          "id": "a_mp3ssu4q_m",
          "point": {
            "x": 165.25136321306152,
            "y": 57.0674097601828
          },
          "inHandle": {
            "x": 173.27145300584334,
            "y": 54.82789106624255
          },
          "outHandle": {
            "x": 157.2312734202797,
            "y": 59.306928454123046
          },
          "handleType": "smooth"
        },
        {
          "id": "a_mp3ssu4q_n",
          "point": {
            "x": 141.29925152562242,
            "y": 64.22955648532347
          },
          "inHandle": {
            "x": 149.2832887547688,
            "y": 61.84217424360991
          },
          "outHandle": {
            "x": 133.31521429647606,
            "y": 66.61693872703702
          },
          "handleType": "smooth"
        },
        {
          "id": "a_mp3ssu4q_o",
          "point": {
            "x": 117.34713983818332,
            "y": 71.39170321046414
          },
          "inHandle": {
            "x": 125.33117706732969,
            "y": 69.00432096875059
          },
          "outHandle": {
            "x": 109.36310260903696,
            "y": 73.7790854521777
          },
          "handleType": "smooth"
        },
        {
          "id": "a_mp3ssu4q_p",
          "point": {
            "x": 93.39502815074422,
            "y": 78.5538499356048
          },
          "inHandle": {
            "x": 101.37906537989059,
            "y": 76.16646769389125
          },
          "outHandle": {
            "x": 85.41099092159786,
            "y": 80.94123217731835
          },
          "handleType": "smooth"
        },
        {
          "id": "a_mp3ssu4q_q",
          "point": {
            "x": 69.44291646330514,
            "y": 85.71599666074547
          },
          "inHandle": {
            "x": 77.37916740310274,
            "y": 85.45235245900089
          },
          "outHandle": {
            "x": 61.50666552350754,
            "y": 85.97964086249006
          },
          "handleType": "smooth"
        },
        {
          "id": "a_mp3ssu4q_r",
          "point": {
            "x": 45.777522511958644,
            "y": 80.1357151460723
          },
          "inHandle": {
            "x": 52.27153028335949,
            "y": 84.20949737778739
          },
          "outHandle": {
            "x": 39.2835147405578,
            "y": 76.06193291435721
          },
          "handleType": "smooth"
        },
        {
          "id": "a_mp3ssu4q_s",
          "point": {
            "x": 30.478869834900067,
            "y": 61.27330327045499
          },
          "inHandle": {
            "x": 32.772024472119696,
            "y": 68.4711307514203
          },
          "outHandle": {
            "x": 28.185715197680437,
            "y": 54.07547578948968
          },
          "handleType": "smooth"
        },
        {
          "id": "a_mp3ssu4q_t",
          "point": {
            "x": 32.018594688640874,
            "y": 36.94875026028044
          },
          "inHandle": {
            "x": 28.841611958738618,
            "y": 43.82772675676743
          },
          "outHandle": {
            "x": 35.19557741854313,
            "y": 30.069773763793453
          },
          "handleType": "smooth"
        },
        {
          "id": "a_mp3ssu4q_u",
          "point": {
            "x": 49.5407662143136,
            "y": 19.999444291533052
          },
          "inHandle": {
            "x": 42.7432297391812,
            "y": 24.35031308467566
          },
          "outHandle": {
            "x": 56.338302689445996,
            "y": 15.648575498390446
          },
          "handleType": "smooth"
        },
        {
          "id": "a_mp3ssu4q_v",
          "point": {
            "x": 72.80381353943525,
            "y": 10.843537501424802
          },
          "inHandle": {
            "x": 65.04946443106137,
            "y": 13.895506431460886
          },
          "outHandle": {
            "x": 80.55816264780914,
            "y": 7.7915685713887175
          },
          "handleType": "smooth"
        },
        {
          "id": "a_mp3ssu4q_w",
          "point": {
            "x": 96.0668608645569,
            "y": 1.6876307113165474
          },
          "inHandle": {
            "x": 88.38628253887107,
            "y": 4.866507451066012
          },
          "outHandle": {
            "x": 103.74743919024273,
            "y": -1.4912460284329168
          },
          "handleType": "smooth"
        },
        {
          "id": "a_mp3ssu4q_x",
          "point": {
            "x": 118.88728349355026,
            "y": -8.229722937071983
          },
          "inHandle": {
            "x": 112.30262319936813,
            "y": -3.565299388289483
          },
          "outHandle": {
            "x": 125.47194378773239,
            "y": -12.894146485854485
          },
          "handleType": "smooth"
        },
        {
          "id": "a_mp3ssu4q_y",
          "point": {
            "x": 135.5748226296497,
            "y": -26.298910581378454
          },
          "inHandle": {
            "x": 131.89781656038122,
            "y": -19.34598335595392
          },
          "outHandle": {
            "x": 139.2518286989182,
            "y": -33.25183780680299
          },
          "handleType": "smooth"
        },
        {
          "id": "a_mp3ssu4q_z",
          "point": {
            "x": 140.9493199091611,
            "y": -49.947286289619186
          },
          "inHandle": {
            "x": 139.95244465572299,
            "y": -41.84045102137595
          },
          "outHandle": {
            "x": 141.9461951625992,
            "y": -58.05412155786242
          },
          "handleType": "smooth"
        },
        {
          "id": "a_mp3ssu4q_10",
          "point": {
            "x": 141.55607415027836,
            "y": -74.93992219083788
          },
          "inHandle": {
            "x": 141.34568759881742,
            "y": -66.60981829109636
          },
          "outHandle": {
            "x": 141.7664607017393,
            "y": -83.27002609057939
          },
          "handleType": "smooth"
        },
        {
          "id": "a_mp3ssu4q_11",
          "point": {
            "x": 142.2116392179267,
            "y": -99.92790968806831
          },
          "inHandle": {
            "x": 141.41544199361212,
            "y": -91.65359432668183
          },
          "outHandle": {
            "x": 143.00783644224126,
            "y": -108.2022250494548
          },
          "handleType": "smooth"
        },
        {
          "id": "a_mp3ssu4q_12",
          "point": {
            "x": 146.33325749616574,
            "y": -124.58581435915677
          },
          "inHandle": {
            "x": 144.70620041926753,
            "y": -116.4291816549286
          },
          "outHandle": {
            "x": 147.96031457306395,
            "y": -132.74244706338493
          },
          "handleType": "smooth"
        },
        {
          "id": "a_mp3ssu4q_13",
          "point": {
            "x": 151.97398167931604,
            "y": -148.86770591343733
          },
          "inHandle": {
            "x": 149.69476697870772,
            "y": -140.87673035588907
          },
          "outHandle": {
            "x": 154.25319637992436,
            "y": -156.8586814709856
          },
          "handleType": "smooth"
        },
        {
          "id": "a_mp3ssu4q_14",
          "point": {
            "x": 160.0085456998156,
            "y": -172.5316677044463
          },
          "inHandle": {
            "x": 156.95479454429153,
            "y": -164.79016673728773
          },
          "outHandle": {
            "x": 163.0622968553397,
            "y": -180.27316867160488
          },
          "handleType": "smooth"
        },
        {
          "id": "a_mp3ssu4q_15",
          "point": {
            "x": 170.29648861246056,
            "y": -195.31671171638885
          },
          "inHandle": {
            "x": 166.92284128947097,
            "y": -187.697908815446
          },
          "outHandle": {
            "x": 173.67013593545016,
            "y": -202.9355146173317
          },
          "handleType": "smooth"
        },
        {
          "id": "a_mp3ssu4q_16",
          "point": {
            "x": 180.25042963775314,
            "y": -218.24448511010343
          },
          "inHandle": {
            "x": 177.03214065038554,
            "y": -210.5592927663576
          },
          "outHandle": {
            "x": 183.46871862512074,
            "y": -225.92967745384925
          },
          "handleType": "smooth"
        },
        {
          "id": "a_mp3ssu4q_17",
          "point": {
            "x": 189.60622253666614,
            "y": -241.42786577886375
          },
          "inHandle": {
            "x": 186.48762490369515,
            "y": -233.70007222261032
          },
          "outHandle": {
            "x": 192.72482016963713,
            "y": -249.15565933511718
          },
          "handleType": "smooth"
        },
        {
          "id": "a_mp3ssu4q_18",
          "point": {
            "x": 198.96201543557913,
            "y": -264.61124644762407
          },
          "inHandle": {
            "x": 196.9676977826203,
            "y": -256.67876619403137
          },
          "outHandle": {
            "x": 200.95633308853797,
            "y": -272.54372670121677
          },
          "handleType": "smooth"
        },
        {
          "id": "a_mp3ssu4q_19",
          "point": {
            "x": 201.5721284544191,
            "y": -289.02274730041984
          },
          "inHandle": {
            "x": 202.8637281418728,
            "y": -281.2559998169517
          },
          "outHandle": {
            "x": 200.2805287669654,
            "y": -296.78949478388796
          },
          "handleType": "smooth"
        },
        {
          "id": "a_mp3ssu4q_1a",
          "point": {
            "x": 191.212417310857,
            "y": -311.2117313484328
          },
          "inHandle": {
            "x": 196.47777533243266,
            "y": -305.4651449639555
          },
          "outHandle": {
            "x": 185.94705928928136,
            "y": -316.95831773291013
          },
          "handleType": "smooth"
        },
        {
          "id": "a_mp3ssu4q_1b",
          "point": {
            "x": 169.97998032496525,
            "y": -323.50226560728385
          },
          "inHandle": {
            "x": 177.5942603663113,
            "y": -321.9251264292162
          },
          "outHandle": {
            "x": 162.36570028361922,
            "y": -325.07940478535147
          },
          "handleType": "smooth"
        },
        {
          "id": "a_mp3ssu4q_1c",
          "point": {
            "x": 145.5267370627807,
            "y": -320.6745664168387
          },
          "inHandle": {
            "x": 152.62911618044225,
            "y": -323.91302262848916
          },
          "outHandle": {
            "x": 138.42435794511917,
            "y": -317.4361102051882
          },
          "handleType": "smooth"
        },
        {
          "id": "a_mp3ssu4q_1d",
          "point": {
            "x": 127.36570561899595,
            "y": -304.07152833738087
          },
          "inHandle": {
            "x": 132.0907583968,
            "y": -310.6320857034163
          },
          "outHandle": {
            "x": 122.64065284119191,
            "y": -297.51097097134544
          },
          "handleType": "smooth"
        },
        {
          "id": "a_mp3ssu4q_1e",
          "point": {
            "x": 117.17642039595647,
            "y": -281.31122222062606
          },
          "inHandle": {
            "x": 120.46694490235224,
            "y": -288.95501681279376
          },
          "outHandle": {
            "x": 113.8858958895607,
            "y": -273.66742762845837
          },
          "handleType": "smooth"
        },
        {
          "id": "a_mp3ssu4q_1f",
          "point": {
            "x": 107.62255858062132,
            "y": -258.2087607843747
          },
          "inHandle": {
            "x": 110.80717918573303,
            "y": -265.9095812631252
          },
          "outHandle": {
            "x": 104.4379379755096,
            "y": -250.50794030562426
          },
          "handleType": "smooth"
        },
        {
          "id": "a_mp3ssu4q_1g",
          "point": {
            "x": 98.06869676528616,
            "y": -235.10629934812334
          },
          "inHandle": {
            "x": 101.25331737039788,
            "y": -242.8071198268738
          },
          "outHandle": {
            "x": 94.88407616017444,
            "y": -227.4054788693729
          },
          "handleType": "smooth"
        },
        {
          "id": "a_mp3ssu4q_1h",
          "point": {
            "x": 88.51483494995102,
            "y": -212.003837911872
          },
          "inHandle": {
            "x": 91.69945555506274,
            "y": -219.70465839062246
          },
          "outHandle": {
            "x": 85.3302143448393,
            "y": -204.30301743312157
          },
          "handleType": "smooth"
        },
        {
          "id": "a_mp3ssu4q_1i",
          "point": {
            "x": 78.96097313461584,
            "y": -188.90137647562065
          },
          "inHandle": {
            "x": 82.14559373972756,
            "y": -196.6021969543711
          },
          "outHandle": {
            "x": 75.77635252950412,
            "y": -181.2005559968702
          },
          "handleType": "smooth"
        },
        {
          "id": "a_mp3ssu4q_1j",
          "point": {
            "x": 69.40711131928069,
            "y": -165.7989150393693
          },
          "inHandle": {
            "x": 72.5917319243924,
            "y": -173.49973551811973
          },
          "outHandle": {
            "x": 66.22249071416897,
            "y": -158.09809456061885
          },
          "handleType": "smooth"
        },
        {
          "id": "a_mp3ssu4q_1k",
          "point": {
            "x": 59.85324950394555,
            "y": -142.69645360311796
          },
          "inHandle": {
            "x": 63.037870109057266,
            "y": -150.3972740818684
          },
          "outHandle": {
            "x": 56.66862889883383,
            "y": -134.99563312436752
          },
          "handleType": "smooth"
        },
        {
          "id": "a_mp3ssu4q_1l",
          "point": {
            "x": 50.299387688610395,
            "y": -119.5939921668666
          },
          "inHandle": {
            "x": 53.48400829372211,
            "y": -127.29481264561704
          },
          "outHandle": {
            "x": 47.11476708349868,
            "y": -111.89317168811615
          },
          "handleType": "smooth"
        },
        {
          "id": "a_mp3ssu4q_1m",
          "point": {
            "x": 40.74552587327524,
            "y": -96.49153073061527
          },
          "inHandle": {
            "x": 43.93014647838696,
            "y": -104.19235120936571
          },
          "outHandle": {
            "x": 37.56090526816352,
            "y": -88.79071025186482
          },
          "handleType": "smooth"
        },
        {
          "id": "a_mp3ssu4q_1n",
          "point": {
            "x": 31.191664057940088,
            "y": -73.3890692943639
          },
          "inHandle": {
            "x": 34.376284663051806,
            "y": -81.08988977311436
          },
          "outHandle": {
            "x": 28.00704345282837,
            "y": -65.68824881561345
          },
          "handleType": "smooth"
        },
        {
          "id": "a_mp3ssu4q_1o",
          "point": {
            "x": 21.637802242604934,
            "y": -50.286607858112546
          },
          "inHandle": {
            "x": 24.822422847716656,
            "y": -57.987428336863005
          },
          "outHandle": {
            "x": 18.453181637493213,
            "y": -42.58578737936209
          },
          "handleType": "smooth"
        },
        {
          "id": "a_mp3ssu4q_1p",
          "point": {
            "x": 12.083940427269766,
            "y": -27.184146421861158
          },
          "inHandle": {
            "x": 15.268561032381486,
            "y": -34.884966900611616
          },
          "outHandle": {
            "x": 8.899319822158047,
            "y": -19.4833259431107
          },
          "handleType": "smooth"
        },
        {
          "id": "a_mp3ssu4q_1q",
          "point": {
            "x": 2.530078611934613,
            "y": -4.081684985609797
          },
          "inHandle": {
            "x": 5.714699217046331,
            "y": -11.782505464360241
          },
          "outHandle": {
            "x": -0.654541993177105,
            "y": 3.6191354931406465
          },
          "handleType": "smooth"
        },
        {
          "id": "a_mp3ssu4q_1r",
          "point": {
            "x": -7.023783203400541,
            "y": 19.020776450641506
          },
          "inHandle": {
            "x": -3.839162598288823,
            "y": 11.319955971891062
          },
          "outHandle": {
            "x": -10.208403808512259,
            "y": 26.72159692939195
          },
          "handleType": "smooth"
        },
        {
          "id": "a_mp3ssu4q_1s",
          "point": {
            "x": -16.577645018735694,
            "y": 42.123237886892866
          },
          "inHandle": {
            "x": -13.393024413623976,
            "y": 34.422417408142415
          },
          "outHandle": {
            "x": -19.762265623847412,
            "y": 49.82405836564332
          },
          "handleType": "smooth"
        },
        {
          "id": "a_mp3ssu4q_1t",
          "point": {
            "x": -26.131506834070848,
            "y": 65.22569932314423
          },
          "inHandle": {
            "x": -22.94688622895913,
            "y": 57.524878844393776
          },
          "outHandle": {
            "x": -29.316127439182566,
            "y": 72.92651980189468
          },
          "handleType": "smooth"
        },
        {
          "id": "a_mp3ssu4q_1u",
          "point": {
            "x": -35.685368649406,
            "y": 88.32816075939559
          },
          "inHandle": {
            "x": -32.50074804429428,
            "y": 80.62734028064513
          },
          "outHandle": {
            "x": -38.86998925451772,
            "y": 96.02898123814605
          },
          "handleType": "smooth"
        },
        {
          "id": "a_mp3ssu4q_1v",
          "point": {
            "x": -45.239230464741155,
            "y": 111.43062219564695
          },
          "inHandle": {
            "x": -42.05460985962944,
            "y": 103.72980171689649
          },
          "outHandle": {
            "x": -48.42385106985287,
            "y": 119.1314426743974
          },
          "handleType": "smooth"
        },
        {
          "id": "a_mp3ssu4q_1w",
          "point": {
            "x": -54.79309228007631,
            "y": 134.5330836318983
          },
          "inHandle": {
            "x": -51.60847167496458,
            "y": 126.83226315314786
          },
          "outHandle": {
            "x": -57.97771288518803,
            "y": 142.23390411064875
          },
          "handleType": "smooth"
        },
        {
          "id": "a_mp3ssu4q_1x",
          "point": {
            "x": -64.34695409541149,
            "y": 157.6355450681496
          },
          "inHandle": {
            "x": -61.162333490299766,
            "y": 149.93472458939917
          },
          "outHandle": {
            "x": -67.53157470052322,
            "y": 165.33636554690005
          },
          "handleType": "smooth"
        },
        {
          "id": "a_mp3ssu4q_1y",
          "point": {
            "x": -73.90081591074667,
            "y": 180.73800650440103
          },
          "inHandle": {
            "x": -70.71619530563495,
            "y": 173.03718602565056
          },
          "outHandle": {
            "x": -77.08543651585839,
            "y": 188.4388269831515
          },
          "handleType": "smooth"
        },
        {
          "id": "a_mp3ssu4q_1z",
          "point": {
            "x": -83.45467772608183,
            "y": 203.8404679406524
          },
          "inHandle": {
            "x": -80.27005712097011,
            "y": 196.13964746190192
          },
          "outHandle": {
            "x": -86.63929833119354,
            "y": 211.54128841940286
          },
          "handleType": "smooth"
        },
        {
          "id": "a_mp3ssu4q_20",
          "point": {
            "x": -93.00853954141698,
            "y": 226.9429293769038
          },
          "inHandle": {
            "x": -89.82391893630526,
            "y": 219.24210889815336
          },
          "outHandle": {
            "x": -96.1931601465287,
            "y": 234.64374985565425
          },
          "handleType": "smooth"
        },
        {
          "id": "a_mp3ssu4q_21",
          "point": {
            "x": -102.56240135675213,
            "y": 250.04539081315505
          },
          "inHandle": {
            "x": -99.37778075164042,
            "y": 242.3445703344046
          },
          "outHandle": {
            "x": -105.74702196186385,
            "y": 257.74621129190547
          },
          "handleType": "smooth"
        },
        {
          "id": "a_mp3ssu4q_22",
          "point": {
            "x": -112.11626317208729,
            "y": 273.1478522494064
          },
          "inHandle": {
            "x": -108.93164256697557,
            "y": 265.44703177065594
          },
          "outHandle": {
            "x": -115.300883777199,
            "y": 280.8486727281569
          },
          "handleType": "smooth"
        },
        {
          "id": "a_mp3ssu4q_23",
          "point": {
            "x": -121.67012498742244,
            "y": 296.2503136856578
          },
          "inHandle": {
            "x": -118.48550438231072,
            "y": 288.5494932069073
          },
          "outHandle": {
            "x": -124.85474559253416,
            "y": 303.95113416440824
          },
          "handleType": "smooth"
        },
        {
          "id": "a_mp3ssu4q_24",
          "point": {
            "x": -131.2239868027576,
            "y": 319.35277512190913
          },
          "inHandle": {
            "x": -128.46282111498732,
            "y": 311.51176127122915
          },
          "outHandle": {
            "x": -133.98515249052787,
            "y": 327.1937889725891
          },
          "handleType": "smooth"
        },
        {
          "id": "a_mp3ssu4q_25",
          "point": {
            "x": -138.237119114044,
            "y": 343.2963967897378
          },
          "inHandle": {
            "x": -136.70947377354287,
            "y": 335.16466499156735
          },
          "outHandle": {
            "x": -139.76476445454512,
            "y": 351.42812858790825
          },
          "handleType": "smooth"
        },
        {
          "id": "a_mp3ssu4q_26",
          "point": {
            "x": -140.3898588457643,
            "y": 368.1431659109319
          },
          "inHandle": {
            "x": -140.43319892313488,
            "y": 359.88025033439686
          },
          "outHandle": {
            "x": -140.34651876839374,
            "y": 376.4060814874669
          },
          "handleType": "smooth"
        },
        {
          "id": "a_mp3ssu4q_27",
          "point": {
            "x": -137.97707864982053,
            "y": 392.8738902489478
          },
          "inHandle": {
            "x": -139.53385584558092,
            "y": 384.77373322932334
          },
          "outHandle": {
            "x": -136.42030145406014,
            "y": 400.9740472685723
          },
          "handleType": "smooth"
        },
        {
          "id": "a_mp3ssu4q_28",
          "point": {
            "x": -131.04919567120203,
            "y": 416.74410802867885
          },
          "inHandle": {
            "x": -133.99786536541689,
            "y": 409.02640913931265
          },
          "outHandle": {
            "x": -128.10052597698717,
            "y": 424.46180691804506
          },
          "handleType": "smooth"
        },
        {
          "id": "a_mp3ssu4q_29",
          "point": {
            "x": -120.2850604845314,
            "y": 439.1800835851451
          },
          "inHandle": {
            "x": -124.64462023059367,
            "y": 432.1796611680416
          },
          "outHandle": {
            "x": -115.92550073846913,
            "y": 446.1805060022486
          },
          "handleType": "smooth"
        },
        {
          "id": "a_mp3ssu4q_2a",
          "point": {
            "x": -104.89183719482838,
            "y": 458.7466425312999
          },
          "inHandle": {
            "x": -110.58915852106557,
            "y": 452.75283260172705
          },
          "outHandle": {
            "x": -99.1945158685912,
            "y": 464.7404524608728
          },
          "handleType": "smooth"
        },
        {
          "id": "a_mp3ssu4q_2b",
          "point": {
            "x": -86.10113252710832,
            "y": 475.14294316258236
          },
          "inHandle": {
            "x": -92.810472394269,
            "y": 470.2892663549773
          },
          "outHandle": {
            "x": -79.39179265994764,
            "y": 479.9966199701874
          },
          "handleType": "smooth"
        },
        {
          "id": "a_mp3ssu4q_2c",
          "point": {
            "x": -64.63579799186434,
            "y": 487.86870337693017
          },
          "inHandle": {
            "x": -72.12158229267985,
            "y": 484.3332823043222
          },
          "outHandle": {
            "x": -57.15001369104883,
            "y": 491.40412444953813
          },
          "handleType": "smooth"
        },
        {
          "id": "a_mp3ssu4q_2d",
          "point": {
            "x": -41.186426722215245,
            "y": 496.35546959822994
          },
          "inHandle": {
            "x": -49.21624946743073,
            "y": 494.329802900886
          },
          "outHandle": {
            "x": -33.15660397699976,
            "y": 498.38113629557387
          },
          "handleType": "smooth"
        },
        {
          "id": "a_mp3ssu4q_2e",
          "point": {
            "x": -16.456861520571447,
            "y": 500.0227035609937
          },
          "inHandle": {
            "x": -24.73657475645423,
            "y": 499.3683328869487
          },
          "outHandle": {
            "x": -8.177148284688665,
            "y": 500.67707423503873
          },
          "handleType": "smooth"
        },
        {
          "id": "a_mp3ssu4q_2f",
          "point": {
            "x": 8.491852693081459,
            "y": 500.2816936425
          },
          "inHandle": {
            "x": 0.16780314646232064,
            "y": 500.3168490511846
          },
          "outHandle": {
            "x": 16.8159022397006,
            "y": 500.2465382338154
          },
          "handleType": "smooth"
        },
        {
          "id": "a_mp3ssu4q_2g",
          "point": {
            "x": 33.48743575914338,
            "y": 499.811771108886
          },
          "inHandle": {
            "x": 25.155574737122734,
            "y": 499.968411953424
          },
          "outHandle": {
            "x": 41.81929678116403,
            "y": 499.655130264348
          },
          "handleType": "smooth"
        },
        {
          "id": "a_mp3ssu4q_2h",
          "point": {
            "x": 58.48301882520532,
            "y": 499.3418485752719
          },
          "inHandle": {
            "x": 50.22108996619451,
            "y": 500.00796265184204
          },
          "outHandle": {
            "x": 66.74494768421613,
            "y": 498.6757344987018
          },
          "handleType": "smooth"
        },
        {
          "id": "a_mp3ssu4q_2i",
          "point": {
            "x": 83.05900891320825,
            "y": 495.81508664946506
          },
          "inHandle": {
            "x": 75.4717812695062,
            "y": 498.57301350979264
          },
          "outHandle": {
            "x": 90.6462365569103,
            "y": 493.0571597891375
          },
          "handleType": "smooth"
        },
        {
          "id": "a_mp3ssu4q_2j",
          "point": {
            "x": 104.00638468741761,
            "y": 482.79428741330656
          },
          "inHandle": {
            "x": 98.36864772884458,
            "y": 488.4889641846944
          },
          "outHandle": {
            "x": 109.64412164599064,
            "y": 477.09961064191873
          },
          "handleType": "smooth"
        },
        {
          "id": "a_mp3ssu4q_2k",
          "point": {
            "x": 116.88543066464639,
            "y": 461.6470260211382
          },
          "inHandle": {
            "x": 114.47735026826035,
            "y": 469.27054367287695
          },
          "outHandle": {
            "x": 119.29351106103243,
            "y": 454.0235083693994
          },
          "handleType": "smooth"
        },
        {
          "id": "a_mp3ssu4q_2l",
          "point": {
            "x": 118.45486706573382,
            "y": 437.0531815028739
          },
          "inHandle": {
            "x": 118.8834706090678,
            "y": 445.26126349949
          },
          "outHandle": {
            "x": 118.02626352239984,
            "y": 428.8450995062578
          },
          "handleType": "smooth"
        },
        {
          "id": "a_mp3ssu4q_2m",
          "point": {
            "x": 114.31380940464254,
            "y": 412.39853404144145
          },
          "inHandle": {
            "x": 115.69416195833963,
            "y": 420.61674986191895
          },
          "outHandle": {
            "x": 112.93345685094545,
            "y": 404.18031822096395
          },
          "handleType": "smooth"
        },
        {
          "id": "a_mp3ssu4q_2n",
          "point": {
            "x": 110.17275174355125,
            "y": 387.74388658000896
          },
          "inHandle": {
            "x": 111.55310429724834,
            "y": 395.96210240048646
          },
          "outHandle": {
            "x": 108.79239918985415,
            "y": 379.52567075953147
          },
          "handleType": "smooth"
        },
        {
          "id": "a_mp3ssu4q_2o",
          "point": {
            "x": 106.03169408245995,
            "y": 363.08923911857653
          },
          "inHandle": {
            "x": 107.41204663615704,
            "y": 371.307454939054
          },
          "outHandle": {
            "x": 104.65134152876286,
            "y": 354.87102329809903
          },
          "handleType": "smooth"
        },
        {
          "id": "a_mp3ssu4q_2p",
          "point": {
            "x": 101.89063642136865,
            "y": 338.4345916571441
          },
          "inHandle": {
            "x": 103.27098897506575,
            "y": 346.6528074776216
          },
          "outHandle": {
            "x": 100.51028386767156,
            "y": 330.2163758366666
          },
          "handleType": "smooth"
        },
        {
          "id": "a_mp3ssu4q_2q",
          "point": {
            "x": 97.74957876027736,
            "y": 313.77994419571166
          },
          "inHandle": {
            "x": 99.12993131397445,
            "y": 321.99816001618916
          },
          "outHandle": {
            "x": 96.36922620658027,
            "y": 305.56172837523417
          },
          "handleType": "smooth"
        },
        {
          "id": "a_mp3ssu4q_2r",
          "point": {
            "x": 93.60852109918606,
            "y": 289.12529673427923
          },
          "inHandle": {
            "x": 94.98887365288316,
            "y": 297.3435125547567
          },
          "outHandle": {
            "x": 92.22816854548897,
            "y": 280.90708091380174
          },
          "handleType": "smooth"
        },
        {
          "id": "a_mp3ssu4q_2s",
          "point": {
            "x": 89.46746343809477,
            "y": 264.4706492728468
          },
          "inHandle": {
            "x": 90.84781599179186,
            "y": 272.6888650933243
          },
          "outHandle": {
            "x": 88.08711088439767,
            "y": 256.2524334523693
          },
          "handleType": "smooth"
        },
        {
          "id": "a_mp3ssu4q_2t",
          "point": {
            "x": 85.32640577700349,
            "y": 239.81600181141434
          },
          "inHandle": {
            "x": 86.70675833070058,
            "y": 248.0342176318918
          },
          "outHandle": {
            "x": 83.9460532233064,
            "y": 231.59778599093687
          },
          "handleType": "smooth"
        },
        {
          "id": "a_mp3ssu4q_2u",
          "point": {
            "x": 81.18534811591219,
            "y": 215.1613543499819
          },
          "inHandle": {
            "x": 82.39256495878621,
            "y": 223.38562900616395
          },
          "outHandle": {
            "x": 79.97813127303817,
            "y": 206.93707969379986
          },
          "handleType": "smooth"
        },
        {
          "id": "a_mp3ssu4q_2v",
          "point": {
            "x": 78.0831047197594,
            "y": 190.47035387432203
          },
          "inHandle": {
            "x": 76.96448681954071,
            "y": 198.28457484925946
          },
          "outHandle": {
            "x": 79.2017226199781,
            "y": 182.6561328993846
          },
          "handleType": "smooth"
        },
        {
          "id": "a_mp3ssu4q_2w",
          "point": {
            "x": 87.89705551722439,
            "y": 168.27602850035726
          },
          "inHandle": {
            "x": 82.55979233342418,
            "y": 173.68264482475163
          },
          "outHandle": {
            "x": 93.23431870102459,
            "y": 162.86941217596288
          },
          "handleType": "smooth"
        },
        {
          "id": "a_mp3ssu4q_2x",
          "point": {
            "x": 110.10668382256061,
            "y": 158.03065592795573
          },
          "inHandle": {
            "x": 102.46154548154622,
            "y": 158.73960156617505
          },
          "outHandle": {
            "x": 117.751822163575,
            "y": 157.32171028973642
          },
          "handleType": "smooth"
        },
        {
          "id": "a_mp3ssu4q_2y",
          "point": {
            "x": 133.76788556331073,
            "y": 164.02235467104134
          },
          "inHandle": {
            "x": 127.31437078532686,
            "y": 159.738249686472
          },
          "outHandle": {
            "x": 140.2214003412946,
            "y": 168.3064596556107
          },
          "handleType": "smooth"
        },
        {
          "id": "a_mp3ssu4q_2z",
          "point": {
            "x": 148.82777249046384,
            "y": 183.7352858353719
          },
          "inHandle": {
            "x": 143.3187442941594,
            "y": 178.01072774340673
          },
          "outHandle": {
            "x": 154.3368006867683,
            "y": 189.4598439273371
          },
          "handleType": "smooth"
        },
        {
          "id": "a_mp3ssu4q_30",
          "point": {
            "x": 166.82205474113746,
            "y": 198.36970322283233
          },
          "inHandle": {
            "x": 160.08245127164355,
            "y": 197.7347083693025
          },
          "outHandle": {
            "x": 173.56165821063138,
            "y": 199.00469807636216
          },
          "handleType": "smooth"
        },
        {
          "id": "a_mp3ssu4q_31",
          "point": {
            "x": 189.26539330742725,
            "y": 187.54525495655088
          },
          "inHandle": {
            "x": 181.7951635616783,
            "y": 191.20692167120256
          },
          "outHandle": {
            "x": 196.7356230531762,
            "y": 183.8835882418992
          },
          "handleType": "smooth"
        },
        {
          "id": "a_mp3ssu4q_32",
          "point": {
            "x": 211.64343321563123,
            "y": 176.39970293492226
          },
          "inHandle": {
            "x": 204.18408657956323,
            "y": 180.1148869421318
          },
          "outHandle": {
            "x": 219.10277985169924,
            "y": 172.68451892771273
          },
          "handleType": "smooth"
        },
        {
          "id": "a_mp3ssu4q_33",
          "point": {
            "x": 234.02147312383522,
            "y": 165.25415091329364
          },
          "inHandle": {
            "x": 226.45517565225705,
            "y": 168.7323811007052
          },
          "outHandle": {
            "x": 241.5877705954134,
            "y": 161.7759207258821
          },
          "handleType": "smooth"
        },
        {
          "id": "a_mp3ssu4q_34",
          "point": {
            "x": 257.0412180451002,
            "y": 155.530321810453
          },
          "inHandle": {
            "x": 249.34429930141303,
            "y": 158.71915538655747
          },
          "outHandle": {
            "x": 264.73813678878736,
            "y": 152.3414882343485
          },
          "handleType": "smooth"
        },
        {
          "id": "a_mp3ssu4q_35",
          "point": {
            "x": 280.20298558595823,
            "y": 146.12114945666667
          },
          "inHandle": {
            "x": 272.4227433637434,
            "y": 149.09905271143805
          },
          "outHandle": {
            "x": 287.98322780817307,
            "y": 143.1432462018953
          },
          "handleType": "smooth"
        },
        {
          "id": "a_mp3ssu4q_36",
          "point": {
            "x": 303.72267137838907,
            "y": 137.66290228182476
          },
          "inHandle": {
            "x": 295.86645619084396,
            "y": 140.43895887095624
          },
          "outHandle": {
            "x": 311.57888656593417,
            "y": 134.88684569269327
          },
          "handleType": "smooth"
        },
        {
          "id": "a_mp3ssu4q_37",
          "point": {
            "x": 327.34027671122874,
            "y": 129.46480992187767
          },
          "inHandle": {
            "x": 319.4216249171405,
            "y": 132.0504380083232
          },
          "outHandle": {
            "x": 335.258928505317,
            "y": 126.87918183543215
          },
          "handleType": "smooth"
        },
        {
          "id": "a_mp3ssu4q_38",
          "point": {
            "x": 351.23458214291855,
            "y": 122.14913376315162
          },
          "inHandle": {
            "x": 343.2405303940008,
            "y": 124.49430605652235
          },
          "outHandle": {
            "x": 359.2286338918363,
            "y": 119.8039614697809
          },
          "handleType": "smooth"
        },
        {
          "id": "a_mp3ssu4q_39",
          "point": {
            "x": 375.3045872047352,
            "y": 115.39377616165335
          },
          "inHandle": {
            "x": 367.2253615195224,
            "y": 117.42269807663534
          },
          "outHandle": {
            "x": 383.383812889948,
            "y": 113.36485424667136
          },
          "handleType": "smooth"
        },
        {
          "id": "a_mp3ssu4q_3a",
          "point": {
            "x": 399.70993625419544,
            "y": 109.97560227325965
          },
          "inHandle": {
            "x": 391.5447831315606,
            "y": 111.61983269077709
          },
          "outHandle": {
            "x": 407.87508937683026,
            "y": 108.33137185574222
          },
          "handleType": "smooth"
        },
        {
          "id": "a_mp3ssu4q_3b",
          "point": {
            "x": 424.2955059405441,
            "y": 105.52839365654872
          },
          "inHandle": {
            "x": 416.07627547921544,
            "y": 106.88052209658045
          },
          "outHandle": {
            "x": 432.51473640187277,
            "y": 104.17626521651698
          },
          "handleType": "smooth"
        },
        {
          "id": "a_mp3ssu4q_3c",
          "point": {
            "x": 449.02531902216737,
            "y": 101.86283163306928
          },
          "inHandle": {
            "x": 440.7820479949596,
            "y": 103.08468564089576
          },
          "outHandle": {
            "x": 457.2685900493751,
            "y": 100.6409776252428
          },
          "handleType": "smooth"
        },
        {
          "id": "a_mp3ssu4q_3d",
          "point": {
            "x": 473.75513210379063,
            "y": 98.19726960958982
          },
          "inHandle": {
            "x": 465.4978489988395,
            "y": 99.29045731377994
          },
          "outHandle": {
            "x": 482.01241520874174,
            "y": 97.10408190539971
          },
          "handleType": "smooth"
        },
        {
          "id": "a_mp3ssu4q_3e",
          "point": {
            "x": 498.56901765187393,
            "y": 95.30370540792859
          },
          "inHandle": {
            "x": 490.2768484818917,
            "y": 96.07655082468698
          },
          "outHandle": {
            "x": 506.86118682185617,
            "y": 94.5308599911702
          },
          "handleType": "smooth"
        },
        {
          "id": "a_mp3ssu4q_3f",
          "point": {
            "x": 523.508147123684,
            "y": 93.56019710903948
          },
          "inHandle": {
            "x": 515.1867180828712,
            "y": 93.93433611723253
          },
          "outHandle": {
            "x": 531.8295761644969,
            "y": 93.18605810084642
          },
          "handleType": "smooth"
        },
        {
          "id": "a_mp3ssu4q_3g",
          "point": {
            "x": 548.4975918967509,
            "y": 93.05887135877025
          },
          "inHandle": {
            "x": 540.1678197337067,
            "y": 93.14670602514045
          },
          "outHandle": {
            "x": 556.8273640597952,
            "y": 92.97103669240005
          },
          "handleType": "smooth"
        },
        {
          "id": "a_mp3ssu4q_3h",
          "point": {
            "x": 573.4867801019498,
            "y": 93.0331891108183
          },
          "inHandle": {
            "x": 565.1699808606221,
            "y": 92.68739708891188
          },
          "outHandle": {
            "x": 581.8035793432774,
            "y": 93.37898113272472
          },
          "handleType": "smooth"
        },
        {
          "id": "a_mp3ssu4q_3i",
          "point": {
            "x": 598.3983873447166,
            "y": 95.13362349020873
          },
          "inHandle": {
            "x": 590.0945182637944,
            "y": 94.43347869707858
          },
          "outHandle": {
            "x": 606.7022564256389,
            "y": 95.83376828333888
          },
          "handleType": "smooth"
        },
        {
          "id": "a_mp3ssu4q_3j",
          "point": {
            "x": 623.3099945874835,
            "y": 97.23405786959918
          },
          "inHandle": {
            "x": 615.0061255065613,
            "y": 96.53391307646903
          },
          "outHandle": {
            "x": 631.6138636684058,
            "y": 97.93420266272933
          },
          "handleType": "smooth"
        },
        {
          "id": "a_mp3ssu4q_3k",
          "point": {
            "x": 648.2216018302504,
            "y": 99.33449224898962
          },
          "inHandle": {
            "x": 639.9958430717058,
            "y": 98.19038680985032
          },
          "outHandle": {
            "x": 656.4473605887949,
            "y": 100.47859768812891
          },
          "handleType": "smooth"
        },
        {
          "id": "a_mp3ssu4q_3l",
          "point": {
            "x": 672.6645471387509,
            "y": 104.09869050443493
          },
          "inHandle": {
            "x": 665.3489195199952,
            "y": 100.80496131866201
          },
          "outHandle": {
            "x": 679.9801747575066,
            "y": 107.39241969020784
          },
          "handleType": "smooth"
        },
        {
          "id": "a_mp3ssu4q_3m",
          "point": {
            "x": 692.1153675427842,
            "y": 119.09686736362715
          },
          "inHandle": {
            "x": 687.3749275118411,
            "y": 112.78465647429537
          },
          "outHandle": {
            "x": 696.8558075737272,
            "y": 125.40907825295893
          },
          "handleType": "smooth"
        },
        {
          "id": "a_mp3ssu4q_3n",
          "point": {
            "x": 701.1071873244093,
            "y": 141.97195584042564
          },
          "inHandle": {
            "x": 700.1127690511244,
            "y": 134.09157314336724
          },
          "outHandle": {
            "x": 702.1016055976943,
            "y": 149.85233853748403
          },
          "handleType": "smooth"
        },
        {
          "id": "a_mp3ssu4q_3o",
          "point": {
            "x": 698.0818771824937,
            "y": 166.3791635459775
          },
          "inHandle": {
            "x": 701.1407947386087,
            "y": 159.1358092509028
          },
          "outHandle": {
            "x": 695.0229596263787,
            "y": 173.62251784105217
          },
          "handleType": "smooth"
        },
        {
          "id": "a_mp3ssu4q_3p",
          "point": {
            "x": 682.7536819877193,
            "y": 185.43208161087372
          },
          "inHandle": {
            "x": 689.0028886999385,
            "y": 180.33521970369884
          },
          "outHandle": {
            "x": 676.5044752755002,
            "y": 190.5289435180486
          },
          "handleType": "smooth"
        },
        {
          "id": "a_mp3ssu4q_3q",
          "point": {
            "x": 660.5866369091788,
            "y": 196.9603349890268
          },
          "inHandle": {
            "x": 668.2058814423816,
            "y": 193.63983454448862
          },
          "outHandle": {
            "x": 652.9673923759759,
            "y": 200.28083543356496
          },
          "handleType": "smooth"
        },
        {
          "id": "a_mp3ssu4q_3r",
          "point": {
            "x": 637.0382147885024,
            "y": 205.35508427810274
          },
          "inHandle": {
            "x": 644.9937432896786,
            "y": 202.91801397244157
          },
          "outHandle": {
            "x": 629.0826862873262,
            "y": 207.7921545837639
          },
          "handleType": "smooth"
        },
        {
          "id": "a_mp3ssu4q_3s",
          "point": {
            "x": 612.8534659021213,
            "y": 211.58275682299384
          },
          "inHandle": {
            "x": 620.9858370947647,
            "y": 209.82885965456808
          },
          "outHandle": {
            "x": 604.7210947094779,
            "y": 213.3366539914196
          },
          "handleType": "smooth"
        },
        {
          "id": "a_mp3ssu4q_3t",
          "point": {
            "x": 588.2439876326421,
            "y": 215.87846728865728
          },
          "inHandle": {
            "x": 596.4676113386034,
            "y": 214.55435074805064
          },
          "outHandle": {
            "x": 580.0203639266807,
            "y": 217.20258382926392
          },
          "handleType": "smooth"
        },
        {
          "id": "a_mp3ssu4q_3u",
          "point": {
            "x": 563.511723666353,
            "y": 219.52745606663368
          },
          "inHandle": {
            "x": 571.5651138129583,
            "y": 217.59527175164592
          },
          "outHandle": {
            "x": 555.4583335197476,
            "y": 221.45964038162143
          },
          "handleType": "smooth"
        },
        {
          "id": "a_mp3ssu4q_3v",
          "point": {
            "x": 539.92364675301,
            "y": 227.4715731785838
          },
          "inHandle": {
            "x": 547.3204594552151,
            "y": 223.85655352903694
          },
          "outHandle": {
            "x": 532.5268340508048,
            "y": 231.08659282813068
          },
          "handleType": "smooth"
        },
        {
          "id": "a_mp3ssu4q_3w",
          "point": {
            "x": 519.1308474531221,
            "y": 241.2175739639149
          },
          "inHandle": {
            "x": 525.0643919202048,
            "y": 235.6962441459935
          },
          "outHandle": {
            "x": 513.1973029860394,
            "y": 246.7389037818363
          },
          "handleType": "smooth"
        },
        {
          "id": "a_mp3ssu4q_3x",
          "point": {
            "x": 504.32237995051395,
            "y": 260.59955208611234
          },
          "inHandle": {
            "x": 506.0972423524205,
            "y": 253.41867316652235
          },
          "outHandle": {
            "x": 502.5475175486074,
            "y": 267.7804310057023
          },
          "handleType": "smooth"
        },
        {
          "id": "a_mp3ssu4q_3y",
          "point": {
            "x": 508.4816730416827,
            "y": 284.3028474814548
          },
          "inHandle": {
            "x": 504.7811848307208,
            "y": 277.4683041357962
          },
          "outHandle": {
            "x": 512.1821612526446,
            "y": 291.13739082711345
          },
          "handleType": "smooth"
        },
        {
          "id": "a_mp3ssu4q_3z",
          "point": {
            "x": 526.5253092162856,
            "y": 301.6068121600643
          },
          "inHandle": {
            "x": 520.1480745199194,
            "y": 296.288074238832
          },
          "outHandle": {
            "x": 532.9025439126517,
            "y": 306.9255500812966
          },
          "handleType": "smooth"
        },
        {
          "id": "a_mp3ssu4q_40",
          "point": {
            "x": 546.7450812198795,
            "y": 316.2152750088488
          },
          "inHandle": {
            "x": 539.8101152624719,
            "y": 311.6432763540503
          },
          "outHandle": {
            "x": 553.6800471772871,
            "y": 320.7872736636473
          },
          "handleType": "smooth"
        },
        {
          "id": "a_mp3ssu4q_41",
          "point": {
            "x": 568.1351049607313,
            "y": 329.0388040888555
          },
          "inHandle": {
            "x": 560.7349455206034,
            "y": 325.2985998413699
          },
          "outHandle": {
            "x": 575.5352644008591,
            "y": 332.7790083363411
          },
          "handleType": "smooth"
        },
        {
          "id": "a_mp3ssu4q_42",
          "point": {
            "x": 591.1460378606462,
            "y": 338.6565004937624
          },
          "inHandle": {
            "x": 583.3393363692378,
            "y": 335.7934187916595
          },
          "outHandle": {
            "x": 598.9527393520546,
            "y": 341.51958219586527
          },
          "handleType": "smooth"
        },
        {
          "id": "a_mp3ssu4q_43",
          "point": {
            "x": 614.9753139091812,
            "y": 346.2172943014729
          },
          "inHandle": {
            "x": 606.8993477549858,
            "y": 344.24546919361677
          },
          "outHandle": {
            "x": 623.0512800633766,
            "y": 348.18911940932907
          },
          "handleType": "smooth"
        },
        {
          "id": "a_mp3ssu4q_44",
          "point": {
            "x": 639.6018347858184,
            "y": 350.48745114089917
          },
          "inHandle": {
            "x": 631.3332092327267,
            "y": 349.7037159706119
          },
          "outHandle": {
            "x": 647.87046033891,
            "y": 351.27118631118645
          },
          "handleType": "smooth"
        },
        {
          "id": "a_mp3ssu4q_45",
          "point": {
            "x": 664.5870672277312,
            "y": 350.9197053231966
          },
          "inHandle": {
            "x": 656.2787290738427,
            "y": 351.08545158971907
          },
          "outHandle": {
            "x": 672.8954053816196,
            "y": 350.7539590566741
          },
          "handleType": "smooth"
        },
        {
          "id": "a_mp3ssu4q_46",
          "point": {
            "x": 689.4518637091492,
            "y": 349.49297354176434
          },
          "inHandle": {
            "x": 682.0118000879353,
            "y": 352.10022035207516
          },
          "outHandle": {
            "x": 696.891927330363,
            "y": 346.88572673145353
          },
          "handleType": "smooth"
        },
        {
          "id": "a_mp3ssu4q_47",
          "point": {
            "x": 709.2274489550146,
            "y": 335.2762244613316
          },
          "inHandle": {
            "x": 704.0653659156968,
            "y": 341.37108023201756
          },
          "outHandle": {
            "x": 714.3895319943323,
            "y": 329.1813686906456
          },
          "handleType": "smooth"
        },
        {
          "id": "a_mp3ssu4q_48",
          "point": {
            "x": 720.4243619450554,
            "y": 312.9238389176485
          },
          "inHandle": {
            "x": 716.6920576150418,
            "y": 320.3746340988762
          },
          "outHandle": {
            "x": 724.1566662750689,
            "y": 305.4730437364208
          },
          "handleType": "smooth"
        },
        {
          "id": "a_mp3ssu4q_49",
          "point": {
            "x": 731.6212749350962,
            "y": 290.5714533739653
          },
          "inHandle": {
            "x": 727.8889706050826,
            "y": 298.022248555193
          },
          "outHandle": {
            "x": 735.3535792651097,
            "y": 283.1206581927376
          },
          "handleType": "smooth"
        },
        {
          "id": "a_mp3ssu4q_4a",
          "point": {
            "x": 742.818187925137,
            "y": 268.21906783028214
          },
          "inHandle": {
            "x": 739.0858835951234,
            "y": 275.66986301150985
          },
          "outHandle": {
            "x": 746.5504922551505,
            "y": 260.76827264905444
          },
          "handleType": "smooth"
        },
        {
          "id": "a_mp3ssu4q_4b",
          "point": {
            "x": 754.0151009151778,
            "y": 245.86668228659903
          },
          "inHandle": {
            "x": 749.933054159414,
            "y": 253.11033863171463
          },
          "outHandle": {
            "x": 758.0971476709415,
            "y": 238.62302594148343
          },
          "handleType": "smooth"
        },
        {
          "id": "a_mp3ssu4q_4c",
          "point": {
            "x": 767.3104684597195,
            "y": 224.75712975958865
          },
          "inHandle": {
            "x": 762.7246273881906,
            "y": 231.70240832573256
          },
          "outHandle": {
            "x": 771.8963095312483,
            "y": 217.81185119344474
          },
          "handleType": "smooth"
        },
        {
          "id": "a_mp3ssu4q_4d",
          "point": {
            "x": 781.5301473443507,
            "y": 204.19501088973553
          },
          "inHandle": {
            "x": 776.7902543828069,
            "y": 211.0490505130199
          },
          "outHandle": {
            "x": 786.2700403058944,
            "y": 197.34097126645116
          },
          "handleType": "smooth"
        },
        {
          "id": "a_mp3ssu4q_4e",
          "point": {
            "x": 795.749826228982,
            "y": 183.63289201988238
          },
          "inHandle": {
            "x": 791.0099332674382,
            "y": 190.48693164316677
          },
          "outHandle": {
            "x": 800.4897191905258,
            "y": 176.77885239659798
          },
          "handleType": "smooth"
        },
        {
          "id": "a_mp3ssu4q_4f",
          "point": {
            "x": 809.9695051136133,
            "y": 163.07077315002925
          },
          "inHandle": {
            "x": 805.4495901587284,
            "y": 170.06441850981602
          },
          "outHandle": {
            "x": 814.4894200684982,
            "y": 156.07712779024249
          },
          "handleType": "smooth"
        },
        {
          "id": "a_mp3ssu4q_4g",
          "point": {
            "x": 822.8693159582917,
            "y": 141.6710198611617
          },
          "inHandle": {
            "x": 819.4194983033719,
            "y": 149.18336338019498
          },
          "outHandle": {
            "x": 826.3191336132115,
            "y": 134.15867634212844
          },
          "handleType": "smooth"
        },
        {
          "id": "a_mp3ssu4q_4h",
          "point": {
            "x": 830.6684110431318,
            "y": 117.9967120358296
          },
          "inHandle": {
            "x": 829.1075221932745,
            "y": 126.08306988782418
          },
          "outHandle": {
            "x": 832.229299892989,
            "y": 109.91035418383503
          },
          "handleType": "smooth"
        },
        {
          "id": "a_mp3ssu4q_4i",
          "point": {
            "x": 832.2346490574358,
            "y": 93.15287274919427
          },
          "inHandle": {
            "x": 832.7543354145446,
            "y": 101.36924047579512
          },
          "outHandle": {
            "x": 831.7149627003271,
            "y": 84.93650502259342
          },
          "handleType": "smooth"
        },
        {
          "id": "a_mp3ssu4q_4j",
          "point": {
            "x": 827.5502929004792,
            "y": 68.69850567622453
          },
          "inHandle": {
            "x": 830.1362337917972,
            "y": 76.50436028474554
          },
          "outHandle": {
            "x": 824.9643520091613,
            "y": 60.89265106770351
          },
          "handleType": "smooth"
        },
        {
          "id": "a_mp3ssu4q_4k",
          "point": {
            "x": 816.719003709528,
            "y": 46.31774509806819
          },
          "inHandle": {
            "x": 821.1018435304659,
            "y": 53.291286031741464
          },
          "outHandle": {
            "x": 812.3361638885901,
            "y": 39.34420416439491
          },
          "handleType": "smooth"
        },
        {
          "id": "a_mp3ssu4q_4l",
          "point": {
            "x": 801.2532539748519,
            "y": 26.85726007418487
          },
          "inHandle": {
            "x": 807.2010783471269,
            "y": 32.53589688454144
          },
          "outHandle": {
            "x": 795.3054296025769,
            "y": 21.17862326382831
          },
          "handleType": "smooth"
        },
        {
          "id": "a_mp3ssu4q_4m",
          "point": {
            "x": 781.0320574758779,
            "y": 12.245924235928808
          },
          "inHandle": {
            "x": 788.2400181608047,
            "y": 16.253951138431525
          },
          "outHandle": {
            "x": 773.8240967909511,
            "y": 8.237897333426092
          },
          "handleType": "smooth"
        },
        {
          "id": "a_mp3ssu4q_4n",
          "point": {
            "x": 758.0054898652911,
            "y": 2.8090986591685803
          },
          "inHandle": {
            "x": 765.9500027181707,
            "y": 5.025189930385366
          },
          "outHandle": {
            "x": 750.0609770124115,
            "y": 0.5930073879517939
          },
          "handleType": "smooth"
        },
        {
          "id": "a_mp3ssu4q_4o",
          "point": {
            "x": 733.3649803586003,
            "y": -1.0506233913719116
          },
          "inHandle": {
            "x": 741.628889370683,
            "y": -0.12599453932040516
          },
          "outHandle": {
            "x": 725.1010713465175,
            "y": -1.975252243423418
          },
          "handleType": "smooth"
        },
        {
          "id": "a_mp3ssu4q_4p",
          "point": {
            "x": 708.4220357927945,
            "y": -2.7386744531404585
          },
          "inHandle": {
            "x": 716.7363506480631,
            "y": -2.1759907658842765
          },
          "outHandle": {
            "x": 700.107720937526,
            "y": -3.3013581403966406
          },
          "handleType": "smooth"
        },
        {
          "id": "a_mp3ssu4q_4q",
          "point": {
            "x": 683.4790912269887,
            "y": -4.426725514909005
          },
          "inHandle": {
            "x": 692.0881401777374,
            "y": -3.8440952571305638
          },
          "outHandle": {
            "x": 674.8700422762399,
            "y": -5.009355772687446
          },
          "handleType": "smooth"
        },
        {
          "id": "a_mp3ssu4q_4r",
          "point": {
            "x": 656.767742088302,
            "y": -6.234455999811104
          },
          "inHandle": {
            "x": 656.767742088302,
            "y": -6.234455999811104
          },
          "outHandle": {
            "x": 656.767742088302,
            "y": -6.234455999811104
          },
          "handleType": "corner"
        }
      ],
      "closed": true,
      "stroke": "#e5e7eb",
      "strokeWidth": 1.5,
      "fill": "none"
    }
  ],
  "checkpoints": [
    {
      "id": "f1_zandvoort_checkpoint_0",
      "kind": "start-finish",
      "pathId": "f1_zandvoort_path_0",
      "segmentIndex": 0,
      "t": 0
    },
    {
      "id": "f1_zandvoort_checkpoint_1",
      "kind": "sector",
      "pathId": "f1_zandvoort_path_0",
      "segmentIndex": 77,
      "t": 0.021607378182504435
    },
    {
      "id": "f1_zandvoort_checkpoint_2",
      "kind": "sector",
      "pathId": "f1_zandvoort_path_0",
      "segmentIndex": 128,
      "t": 0.9304894847620075
    }
  ],
  "raceDirection": "forward",
  "pitBoxAreas": []
}